<?xml version="1.0" encoding="UTF-8"?>
<mesh>
    <sharedgeometry vertexcount="29">
        <vertexbuffer texture_coords="1" positions="true" colours_diffuse="False" normals="true">
            <vertex>
                <position y="-173.235504" x="0.000000" z="-95.505203"/>
                <normal y="-0.501450" x="0.013001" z="-0.865078"/>
                <texcoord u="0.500000" v="1.000000"/>
            </vertex>
            <vertex>
                <position y="-172.706497" x="0.414200" z="-95.805603"/>
                <normal y="0.216529" x="0.434553" z="-0.874203"/>
                <texcoord u="0.916700" v="1.000000"/>
            </vertex>
            <vertex>
                <position y="-172.954605" x="0.662900" z="-95.657997"/>
                <normal y="-0.038667" x="0.690481" z="-0.722282"/>
                <texcoord u="0.833300" v="1.000000"/>
            </vertex>
            <vertex>
                <position y="-173.277893" x="0.733900" z="-95.469498"/>
                <normal y="-0.371197" x="0.763543" z="-0.528367"/>
                <texcoord u="0.750000" v="1.000000"/>
            </vertex>
            <vertex>
                <position y="-172.664001" x="-0.319700" z="-95.841202"/>
                <normal y="0.260384" x="-0.320383" z="-0.910764"/>
                <texcoord u="0.083300" v="1.000000"/>
            </vertex>
            <vertex>
                <position y="-172.600098" x="0.054600" z="-95.872597"/>
                <normal y="0.326121" x="0.064577" z="-0.943083"/>
                <texcoord u="0.000000" v="1.000000"/>
            </vertex>
            <vertex>
                <position y="-172.706497" x="0.414200" z="-95.805603"/>
                <normal y="0.216529" x="0.434553" z="-0.874203"/>
                <texcoord u="-0.083300" v="1.000000"/>
            </vertex>
            <vertex>
                <position y="-173.192993" x="-0.733900" z="-95.540802"/>
                <normal y="-0.283883" x="-0.746513" z="-0.601733"/>
                <texcoord u="0.250000" v="1.000000"/>
            </vertex>
            <vertex>
                <position y="-172.880997" x="-0.608300" z="-95.719803"/>
                <normal y="0.037111" x="-0.617267" z="-0.785852"/>
                <texcoord u="0.166700" v="1.000000"/>
            </vertex>
            <vertex>
                <position y="-173.764496" x="-0.414200" z="-95.204697"/>
                <normal y="-0.871792" x="-0.417646" z="-0.255959"/>
                <texcoord u="0.416700" v="1.000000"/>
            </vertex>
            <vertex>
                <position y="-173.516403" x="-0.662900" z="-95.352303"/>
                <normal y="-0.616565" x="-0.673421" z="-0.407819"/>
                <texcoord u="0.333300" v="1.000000"/>
            </vertex>
            <vertex>
                <position y="-173.806900" x="0.319700" z="-95.169098"/>
                <normal y="-0.915433" x="0.337382" z="-0.219337"/>
                <texcoord u="0.583300" v="1.000000"/>
            </vertex>
            <vertex>
                <position y="-173.870804" x="-0.054600" z="-95.137703"/>
                <normal y="-0.981170" x="-0.047609" z="-0.187109"/>
                <texcoord u="0.500000" v="1.000000"/>
            </vertex>
            <vertex>
                <position y="-173.589905" x="0.608300" z="-95.290604"/>
                <normal y="-0.692160" x="0.634266" z="-0.344371"/>
                <texcoord u="0.666700" v="1.000000"/>
            </vertex>
            <vertex>
                <position y="-172.774002" x="0.658200" z="-95.346603"/>
                <normal y="0.616535" x="0.673452" z="0.407788"/>
                <texcoord u="0.833300" v="0.000000"/>
            </vertex>
            <vertex>
                <position y="-173.097397" x="0.729200" z="-95.158096"/>
                <normal y="0.283883" x="0.746513" z="0.601733"/>
                <texcoord u="0.750000" v="0.000000"/>
            </vertex>
            <vertex>
                <position y="-172.525894" x="0.409600" z="-95.494202"/>
                <normal y="0.871792" x="0.417707" z="0.255837"/>
                <texcoord u="0.916700" v="0.000000"/>
            </vertex>
            <vertex>
                <position y="-172.419601" x="0.049900" z="-95.561203"/>
                <normal y="0.981170" x="0.047609" z="0.187017"/>
                <texcoord u="0.000000" v="0.000000"/>
            </vertex>
            <vertex>
                <position y="-172.525894" x="0.409600" z="-95.494202"/>
                <normal y="0.871792" x="0.417707" z="0.255837"/>
                <texcoord u="-0.083300" v="0.000000"/>
            </vertex>
            <vertex>
                <position y="-172.483505" x="-0.324300" z="-95.529800"/>
                <normal y="0.915464" x="-0.337260" z="0.219337"/>
                <texcoord u="0.083300" v="0.000000"/>
            </vertex>
            <vertex>
                <position y="-172.700500" x="-0.613000" z="-95.408302"/>
                <normal y="0.692190" x="-0.634236" z="0.344340"/>
                <texcoord u="0.166700" v="0.000000"/>
            </vertex>
            <vertex>
                <position y="-173.012497" x="-0.738600" z="-95.229401"/>
                <normal y="0.371166" x="-0.763543" z="0.528367"/>
                <texcoord u="0.250000" v="0.000000"/>
            </vertex>
            <vertex>
                <position y="-173.335800" x="-0.667600" z="-95.040901"/>
                <normal y="0.038606" x="-0.690451" z="0.722312"/>
                <texcoord u="0.333300" v="0.000000"/>
            </vertex>
            <vertex>
                <position y="-173.584000" x="-0.418900" z="-94.893303"/>
                <normal y="-0.216712" x="-0.434675" z="0.874081"/>
                <texcoord u="0.416700" v="0.000000"/>
            </vertex>
            <vertex>
                <position y="-173.690308" x="-0.059300" z="-94.826202"/>
                <normal y="-0.326090" x="-0.064608" z="0.943114"/>
                <texcoord u="0.500000" v="0.000000"/>
            </vertex>
            <vertex>
                <position y="-173.626404" x="0.315000" z="-94.857697"/>
                <normal y="-0.260384" x="0.320414" z="0.910764"/>
                <texcoord u="0.583300" v="0.000000"/>
            </vertex>
            <vertex>
                <position y="-173.409393" x="0.603600" z="-94.979103"/>
                <normal y="-0.037049" x="0.617298" z="0.785852"/>
                <texcoord u="0.666700" v="0.000000"/>
            </vertex>
            <vertex>
                <position y="-173.054901" x="-0.004700" z="-95.193703"/>
                <normal y="0.501450" x="-0.013001" z="0.865078"/>
                <texcoord u="0.500000" v="0.000000"/>
            </vertex>
            <vertex>
                <position y="-172.419601" x="0.049900" z="-95.561203"/>
                <normal y="0.981170" x="0.047609" z="0.187017"/>
                <texcoord u="0.888400" v="0.000000"/>
            </vertex>
        </vertexbuffer>
    </sharedgeometry>
    <submeshes>
        <submesh usesharedvertices="true" material="rope_" use32bitindexes="False" operationtype="triangle_list">
            <faces count="48">
                <face v1="0" v2="1" v3="2"/>
                <face v1="0" v2="2" v3="3"/>
                <face v1="0" v2="4" v3="5"/>
                <face v1="0" v2="5" v3="6"/>
                <face v1="0" v2="7" v3="8"/>
                <face v1="0" v2="8" v3="4"/>
                <face v1="0" v2="9" v3="10"/>
                <face v1="0" v2="10" v3="7"/>
                <face v1="0" v2="11" v3="12"/>
                <face v1="0" v2="12" v3="9"/>
                <face v1="0" v2="3" v3="13"/>
                <face v1="0" v2="13" v3="11"/>
                <face v1="3" v2="2" v3="14"/>
                <face v1="3" v2="14" v3="15"/>
                <face v1="2" v2="1" v3="16"/>
                <face v1="2" v2="16" v3="14"/>
                <face v1="6" v2="5" v3="17"/>
                <face v1="6" v2="17" v3="18"/>
                <face v1="5" v2="4" v3="19"/>
                <face v1="5" v2="19" v3="17"/>
                <face v1="4" v2="8" v3="20"/>
                <face v1="4" v2="20" v3="19"/>
                <face v1="8" v2="7" v3="21"/>
                <face v1="8" v2="21" v3="20"/>
                <face v1="7" v2="10" v3="22"/>
                <face v1="7" v2="22" v3="21"/>
                <face v1="10" v2="9" v3="23"/>
                <face v1="10" v2="23" v3="22"/>
                <face v1="9" v2="12" v3="24"/>
                <face v1="9" v2="24" v3="23"/>
                <face v1="12" v2="11" v3="25"/>
                <face v1="12" v2="25" v3="24"/>
                <face v1="11" v2="13" v3="26"/>
                <face v1="11" v2="26" v3="25"/>
                <face v1="13" v2="3" v3="15"/>
                <face v1="13" v2="15" v3="26"/>
                <face v1="27" v2="26" v3="15"/>
                <face v1="27" v2="15" v3="14"/>
                <face v1="27" v2="14" v3="16"/>
                <face v1="27" v2="16" v3="28"/>
                <face v1="27" v2="17" v3="19"/>
                <face v1="27" v2="19" v3="20"/>
                <face v1="27" v2="20" v3="21"/>
                <face v1="27" v2="21" v3="22"/>
                <face v1="27" v2="22" v3="23"/>
                <face v1="27" v2="23" v3="24"/>
                <face v1="27" v2="24" v3="25"/>
                <face v1="27" v2="25" v3="26"/>
            </faces>
        </submesh>
    </submeshes>
    <submeshnames>
        <submesh index="0" name="rope_">
        </submesh>
    </submeshnames>
</mesh>