<?xml version="1.0" encoding="UTF-8"?>
<mesh>
    <sharedgeometry vertexcount="29">
        <vertexbuffer texture_coords="1" positions="true" colours_diffuse="False" normals="true">
            <vertex>
                <position y="-150.563599" x="-11.259300" z="-129.050903"/>
                <normal y="0.002899" x="0.990753" z="0.135502"/>
                <texcoord u="0.500000" v="1.000000"/>
            </vertex>
            <vertex>
                <position y="-149.661606" x="-11.082900" z="-130.360596"/>
                <normal y="0.428755" x="0.730674" z="-0.531266"/>
                <texcoord u="0.916700" v="1.000000"/>
            </vertex>
            <vertex>
                <position y="-149.121704" x="-11.169500" z="-129.738602"/>
                <normal y="0.684255" x="0.689657" z="-0.236885"/>
                <texcoord u="0.833300" v="1.000000"/>
            </vertex>
            <vertex>
                <position y="-148.968201" x="-11.280300" z="-128.932297"/>
                <normal y="0.756920" x="0.637257" z="0.144658"/>
                <texcoord u="0.750000" v="1.000000"/>
            </vertex>
            <vertex>
                <position y="-151.257095" x="-11.061900" z="-130.479294"/>
                <normal y="-0.326212" x="0.740593" z="-0.587420"/>
                <texcoord u="0.083300" v="1.000000"/>
            </vertex>
            <vertex>
                <position y="-150.443207" x="-11.043500" z="-130.631699"/>
                <normal y="0.058931" x="0.749321" z="-0.659536"/>
                <texcoord u="0.000000" v="1.000000"/>
            </vertex>
            <vertex>
                <position y="-149.661606" x="-11.082900" z="-130.360596"/>
                <normal y="0.428755" x="0.730674" z="-0.531266"/>
                <texcoord u="-0.083300" v="1.000000"/>
            </vertex>
            <vertex>
                <position y="-152.159103" x="-11.238400" z="-129.169601"/>
                <normal y="-0.753105" x="0.657094" z="0.032319"/>
                <texcoord u="0.250000" v="1.000000"/>
            </vertex>
            <vertex>
                <position y="-151.885101" x="-11.133300" z="-129.944107"/>
                <normal y="-0.623463" x="0.706839" z="-0.334117"/>
                <texcoord u="0.166700" v="1.000000"/>
            </vertex>
            <vertex>
                <position y="-151.465698" x="-11.435800" z="-127.741302"/>
                <normal y="-0.424909" x="0.563646" z="0.708304"/>
                <texcoord u="0.416700" v="1.000000"/>
            </vertex>
            <vertex>
                <position y="-152.005600" x="-11.349100" z="-128.363297"/>
                <normal y="-0.680441" x="0.604694" z="0.413892"/>
                <texcoord u="0.333300" v="1.000000"/>
            </vertex>
            <vertex>
                <position y="-149.870193" x="-11.456700" z="-127.622597"/>
                <normal y="0.330027" x="0.553789" z="0.764428"/>
                <texcoord u="0.583300" v="1.000000"/>
            </vertex>
            <vertex>
                <position y="-150.684097" x="-11.475200" z="-127.470200"/>
                <normal y="-0.055086" x="0.545030" z="0.836573"/>
                <texcoord u="0.500000" v="1.000000"/>
            </vertex>
            <vertex>
                <position y="-149.242096" x="-11.385400" z="-128.157806"/>
                <normal y="0.627308" x="0.587512" z="0.511155"/>
                <texcoord u="0.666700" v="1.000000"/>
            </vertex>
            <vertex>
                <position y="-149.124695" x="-12.160300" z="-129.874100"/>
                <normal y="0.680410" x="-0.604694" z="-0.413923"/>
                <texcoord u="0.833300" v="0.000000"/>
            </vertex>
            <vertex>
                <position y="-148.971100" x="-12.271000" z="-129.067795"/>
                <normal y="0.753105" x="-0.657063" z="-0.032350"/>
                <texcoord u="0.750000" v="0.000000"/>
            </vertex>
            <vertex>
                <position y="-149.664597" x="-12.073700" z="-130.496094"/>
                <normal y="0.424879" x="-0.563738" z="-0.708243"/>
                <texcoord u="0.916700" v="0.000000"/>
            </vertex>
            <vertex>
                <position y="-150.446198" x="-12.034300" z="-130.767197"/>
                <normal y="0.055055" x="-0.545061" z="-0.836543"/>
                <texcoord u="0.000000" v="0.000000"/>
            </vertex>
            <vertex>
                <position y="-149.664597" x="-12.073700" z="-130.496094"/>
                <normal y="0.424879" x="-0.563738" z="-0.708243"/>
                <texcoord u="-0.083300" v="0.000000"/>
            </vertex>
            <vertex>
                <position y="-151.259995" x="-12.052700" z="-130.614807"/>
                <normal y="-0.330058" x="-0.553758" z="-0.764428"/>
                <texcoord u="0.083300" v="0.000000"/>
            </vertex>
            <vertex>
                <position y="-151.888107" x="-12.124000" z="-130.079605"/>
                <normal y="-0.627308" x="-0.587481" z="-0.511155"/>
                <texcoord u="0.166700" v="0.000000"/>
            </vertex>
            <vertex>
                <position y="-152.162003" x="-12.229200" z="-129.305099"/>
                <normal y="-0.756859" x="-0.637318" z="-0.144688"/>
                <texcoord u="0.250000" v="0.000000"/>
            </vertex>
            <vertex>
                <position y="-152.008499" x="-12.339900" z="-128.498795"/>
                <normal y="-0.684225" x="-0.689688" z="0.236854"/>
                <texcoord u="0.333300" v="0.000000"/>
            </vertex>
            <vertex>
                <position y="-151.468597" x="-12.426500" z="-127.876801"/>
                <normal y="-0.428724" x="-0.730674" z="0.531266"/>
                <texcoord u="0.416700" v="0.000000"/>
            </vertex>
            <vertex>
                <position y="-150.686996" x="-12.465900" z="-127.605698"/>
                <normal y="-0.058901" x="-0.749321" z="0.659536"/>
                <texcoord u="0.500000" v="0.000000"/>
            </vertex>
            <vertex>
                <position y="-149.873093" x="-12.447500" z="-127.758102"/>
                <normal y="0.326212" x="-0.740593" z="0.587420"/>
                <texcoord u="0.583300" v="0.000000"/>
            </vertex>
            <vertex>
                <position y="-149.245102" x="-12.376200" z="-128.293304"/>
                <normal y="0.623402" x="-0.706870" z="0.334117"/>
                <texcoord u="0.666700" v="0.000000"/>
            </vertex>
            <vertex>
                <position y="-150.566605" x="-12.250100" z="-129.186401"/>
                <normal y="-0.002930" x="-0.990753" z="-0.135472"/>
                <texcoord u="0.500000" v="0.000000"/>
            </vertex>
            <vertex>
                <position y="-150.446198" x="-12.034300" z="-130.767197"/>
                <normal y="0.055055" x="-0.545061" z="-0.836543"/>
                <texcoord u="0.888400" v="0.000000"/>
            </vertex>
        </vertexbuffer>
    </sharedgeometry>
    <submeshes>
        <submesh usesharedvertices="true" material="hull_trim_wood" use32bitindexes="False" operationtype="triangle_list">
            <faces count="48">
                <face v1="0" v2="1" v3="2"/>
                <face v1="0" v2="2" v3="3"/>
                <face v1="0" v2="4" v3="5"/>
                <face v1="0" v2="5" v3="6"/>
                <face v1="0" v2="7" v3="8"/>
                <face v1="0" v2="8" v3="4"/>
                <face v1="0" v2="9" v3="10"/>
                <face v1="0" v2="10" v3="7"/>
                <face v1="0" v2="11" v3="12"/>
                <face v1="0" v2="12" v3="9"/>
                <face v1="0" v2="3" v3="13"/>
                <face v1="0" v2="13" v3="11"/>
                <face v1="3" v2="2" v3="14"/>
                <face v1="3" v2="14" v3="15"/>
                <face v1="2" v2="1" v3="16"/>
                <face v1="2" v2="16" v3="14"/>
                <face v1="6" v2="5" v3="17"/>
                <face v1="6" v2="17" v3="18"/>
                <face v1="5" v2="4" v3="19"/>
                <face v1="5" v2="19" v3="17"/>
                <face v1="4" v2="8" v3="20"/>
                <face v1="4" v2="20" v3="19"/>
                <face v1="8" v2="7" v3="21"/>
                <face v1="8" v2="21" v3="20"/>
                <face v1="7" v2="10" v3="22"/>
                <face v1="7" v2="22" v3="21"/>
                <face v1="10" v2="9" v3="23"/>
                <face v1="10" v2="23" v3="22"/>
                <face v1="9" v2="12" v3="24"/>
                <face v1="9" v2="24" v3="23"/>
                <face v1="12" v2="11" v3="25"/>
                <face v1="12" v2="25" v3="24"/>
                <face v1="11" v2="13" v3="26"/>
                <face v1="11" v2="26" v3="25"/>
                <face v1="13" v2="3" v3="15"/>
                <face v1="13" v2="15" v3="26"/>
                <face v1="27" v2="26" v3="15"/>
                <face v1="27" v2="15" v3="14"/>
                <face v1="27" v2="14" v3="16"/>
                <face v1="27" v2="16" v3="28"/>
                <face v1="27" v2="17" v3="19"/>
                <face v1="27" v2="19" v3="20"/>
                <face v1="27" v2="20" v3="21"/>
                <face v1="27" v2="21" v3="22"/>
                <face v1="27" v2="22" v3="23"/>
                <face v1="27" v2="23" v3="24"/>
                <face v1="27" v2="24" v3="25"/>
                <face v1="27" v2="25" v3="26"/>
            </faces>
        </submesh>
    </submeshes>
    <submeshnames>
        <submesh index="0" name="hull_trim_wood">
        </submesh>
    </submeshnames>
</mesh>