<?xml version="1.0" encoding="UTF-8"?>
<mesh>
    <sharedgeometry vertexcount="294">
        <vertexbuffer texture_coords="1" positions="true" colours_diffuse="False" normals="true">
            <vertex>
                <position y="143.518402" x="30.038500" z="-1.165300"/>
                <normal y="-0.709799" x="-0.704001" z="0.023011"/>
                <texcoord u="0.034800" v="0.834700"/>
            </vertex>
            <vertex>
                <position y="143.694794" x="29.807199" z="-2.800400"/>
                <normal y="-0.709861" x="-0.703940" z="0.022980"/>
                <texcoord u="0.027900" v="0.669900"/>
            </vertex>
            <vertex>
                <position y="143.550095" x="29.951900" z="-2.836400"/>
                <normal y="-0.709677" x="-0.704123" z="0.023041"/>
                <texcoord u="0.027900" v="0.669900"/>
            </vertex>
            <vertex>
                <position y="143.373703" x="30.183201" z="-1.201400"/>
                <normal y="-0.709738" x="-0.704062" z="0.023011"/>
                <texcoord u="0.034800" v="0.834700"/>
            </vertex>
            <vertex>
                <position y="143.871201" x="29.575899" z="-4.435400"/>
                <normal y="-0.709891" x="-0.703909" z="0.022980"/>
                <texcoord u="0.021100" v="0.505100"/>
            </vertex>
            <vertex>
                <position y="143.726501" x="29.720600" z="-4.471500"/>
                <normal y="-0.709677" x="-0.704123" z="0.023041"/>
                <texcoord u="0.021100" v="0.505100"/>
            </vertex>
            <vertex>
                <position y="144.047607" x="29.344500" z="-6.070400"/>
                <normal y="-0.709891" x="-0.703909" z="0.022980"/>
                <texcoord u="0.014200" v="0.340300"/>
            </vertex>
            <vertex>
                <position y="143.902893" x="29.489300" z="-6.106500"/>
                <normal y="-0.709738" x="-0.704062" z="0.023011"/>
                <texcoord u="0.014200" v="0.340300"/>
            </vertex>
            <vertex>
                <position y="144.223999" x="29.113199" z="-7.705500"/>
                <normal y="-0.709861" x="-0.703940" z="0.022980"/>
                <texcoord u="0.007400" v="0.175500"/>
            </vertex>
            <vertex>
                <position y="144.079300" x="29.257999" z="-7.741600"/>
                <normal y="-0.709769" x="-0.704031" z="0.023011"/>
                <texcoord u="0.007400" v="0.175500"/>
            </vertex>
            <vertex>
                <position y="143.405304" x="30.096600" z="-2.872500"/>
                <normal y="-0.709738" x="-0.704062" z="0.023041"/>
                <texcoord u="0.027900" v="0.669900"/>
            </vertex>
            <vertex>
                <position y="143.228897" x="30.327999" z="-1.237500"/>
                <normal y="-0.709769" x="-0.704031" z="0.023011"/>
                <texcoord u="0.034800" v="0.834700"/>
            </vertex>
            <vertex>
                <position y="143.581696" x="29.865299" z="-4.507600"/>
                <normal y="-0.709677" x="-0.704123" z="0.023041"/>
                <texcoord u="0.021100" v="0.505100"/>
            </vertex>
            <vertex>
                <position y="143.758102" x="29.634001" z="-6.142600"/>
                <normal y="-0.709647" x="-0.704154" z="0.023041"/>
                <texcoord u="0.014200" v="0.340300"/>
            </vertex>
            <vertex>
                <position y="143.934494" x="29.402700" z="-7.777600"/>
                <normal y="-0.709677" x="-0.704123" z="0.023041"/>
                <texcoord u="0.007400" v="0.175500"/>
            </vertex>
            <vertex>
                <position y="143.260605" x="30.241400" z="-2.908600"/>
                <normal y="-0.709861" x="-0.703940" z="0.023011"/>
                <texcoord u="0.027900" v="0.669900"/>
            </vertex>
            <vertex>
                <position y="143.084198" x="30.472700" z="-1.273600"/>
                <normal y="-0.709799" x="-0.704001" z="0.023011"/>
                <texcoord u="0.034800" v="0.834700"/>
            </vertex>
            <vertex>
                <position y="143.436996" x="30.010000" z="-4.543700"/>
                <normal y="-0.709891" x="-0.703909" z="0.022980"/>
                <texcoord u="0.021100" v="0.505100"/>
            </vertex>
            <vertex>
                <position y="143.613403" x="29.778700" z="-6.178700"/>
                <normal y="-0.709861" x="-0.703940" z="0.022980"/>
                <texcoord u="0.014200" v="0.340300"/>
            </vertex>
            <vertex>
                <position y="143.789795" x="29.547400" z="-7.813700"/>
                <normal y="-0.709799" x="-0.704001" z="0.023011"/>
                <texcoord u="0.007400" v="0.175500"/>
            </vertex>
            <vertex>
                <position y="143.115906" x="30.386101" z="-2.944700"/>
                <normal y="-0.709799" x="-0.704001" z="0.023011"/>
                <texcoord u="0.027900" v="0.669900"/>
            </vertex>
            <vertex>
                <position y="142.939499" x="30.617399" z="-1.309700"/>
                <normal y="-0.709769" x="-0.704031" z="0.023011"/>
                <texcoord u="0.034800" v="0.834700"/>
            </vertex>
            <vertex>
                <position y="143.292297" x="30.154800" z="-4.579800"/>
                <normal y="-0.709861" x="-0.703940" z="0.022980"/>
                <texcoord u="0.021100" v="0.505100"/>
            </vertex>
            <vertex>
                <position y="143.468704" x="29.923500" z="-6.214800"/>
                <normal y="-0.709891" x="-0.703909" z="0.022980"/>
                <texcoord u="0.014200" v="0.340300"/>
            </vertex>
            <vertex>
                <position y="143.645096" x="29.692101" z="-7.849800"/>
                <normal y="-0.709891" x="-0.703909" z="0.022980"/>
                <texcoord u="0.007400" v="0.175500"/>
            </vertex>
            <vertex>
                <position y="143.341995" x="30.269800" z="0.469700"/>
                <normal y="-0.580706" x="-0.404462" z="0.706504"/>
                <texcoord u="0.041600" v="0.999500"/>
            </vertex>
            <vertex>
                <position y="143.486694" x="30.125099" z="0.505800"/>
                <normal y="-0.071108" x="-0.732658" z="0.676840"/>
                <texcoord u="0.041600" v="0.999500"/>
            </vertex>
            <vertex>
                <position y="143.663101" x="29.893801" z="-1.129200"/>
                <normal y="-0.009583" x="-0.990234" z="0.139042"/>
                <texcoord u="0.034800" v="0.834700"/>
            </vertex>
            <vertex>
                <position y="144.400406" x="28.881901" z="-9.340500"/>
                <normal y="-0.423414" x="-0.593951" z="-0.684011"/>
                <texcoord u="0.000500" v="0.010700"/>
            </vertex>
            <vertex>
                <position y="144.368698" x="28.968500" z="-7.669400"/>
                <normal y="-0.009491" x="-0.990234" z="0.139042"/>
                <texcoord u="0.007400" v="0.175500"/>
            </vertex>
            <vertex>
                <position y="144.545105" x="28.737200" z="-9.304400"/>
                <normal y="0.055696" x="-0.886868" z="-0.458602"/>
                <texcoord u="0.000500" v="0.010700"/>
            </vertex>
            <vertex>
                <position y="143.676804" x="29.605600" z="-9.520900"/>
                <normal y="-0.747612" x="-0.083407" z="-0.658834"/>
                <texcoord u="0.000500" v="0.010700"/>
            </vertex>
            <vertex>
                <position y="143.500397" x="29.836901" z="-7.885900"/>
                <normal y="-0.994293" x="-0.005280" z="-0.106510"/>
                <texcoord u="0.007400" v="0.175500"/>
            </vertex>
            <vertex>
                <position y="143.821503" x="29.460800" z="-9.484900"/>
                <normal y="-0.423566" x="-0.593768" z="-0.684072"/>
                <texcoord u="0.000500" v="0.010700"/>
            </vertex>
            <vertex>
                <position y="142.763107" x="30.848700" z="0.325400"/>
                <normal y="-0.580554" x="-0.404431" z="0.706626"/>
                <texcoord u="0.041600" v="0.999500"/>
            </vertex>
            <vertex>
                <position y="142.794800" x="30.762100" z="-1.345800"/>
                <normal y="-0.994293" x="-0.005432" z="-0.106510"/>
                <texcoord u="0.034800" v="0.834700"/>
            </vertex>
            <vertex>
                <position y="142.618301" x="30.993500" z="0.289300"/>
                <normal y="-0.876370" x="0.072817" z="0.476028"/>
                <texcoord u="0.041600" v="0.999500"/>
            </vertex>
            <vertex>
                <position y="143.839493" x="29.662399" z="-2.764300"/>
                <normal y="-0.009735" x="-0.990234" z="0.139042"/>
                <texcoord u="0.027900" v="0.669900"/>
            </vertex>
            <vertex>
                <position y="144.255707" x="29.026600" z="-9.376600"/>
                <normal y="-0.423383" x="-0.593982" z="-0.684011"/>
                <texcoord u="0.000500" v="0.010700"/>
            </vertex>
            <vertex>
                <position y="143.324005" x="30.068199" z="-6.250900"/>
                <normal y="-0.994293" x="-0.005371" z="-0.106479"/>
                <texcoord u="0.014200" v="0.340300"/>
            </vertex>
            <vertex>
                <position y="142.907806" x="30.704000" z="0.361400"/>
                <normal y="-0.580645" x="-0.404523" z="0.706504"/>
                <texcoord u="0.041600" v="0.999500"/>
            </vertex>
            <vertex>
                <position y="144.015900" x="29.431101" z="-4.399300"/>
                <normal y="-0.009552" x="-0.990234" z="0.139042"/>
                <texcoord u="0.021100" v="0.505100"/>
            </vertex>
            <vertex>
                <position y="144.110901" x="29.171400" z="-9.412700"/>
                <normal y="-0.423353" x="-0.594073" z="-0.683981"/>
                <texcoord u="0.000500" v="0.010700"/>
            </vertex>
            <vertex>
                <position y="143.147598" x="30.299500" z="-4.615800"/>
                <normal y="-0.994293" x="-0.005432" z="-0.106479"/>
                <texcoord u="0.021100" v="0.505100"/>
            </vertex>
            <vertex>
                <position y="143.052505" x="30.559299" z="0.397500"/>
                <normal y="-0.580676" x="-0.404431" z="0.706534"/>
                <texcoord u="0.041600" v="0.999500"/>
            </vertex>
            <vertex>
                <position y="144.192307" x="29.199800" z="-6.034300"/>
                <normal y="-0.009522" x="-0.990234" z="0.139042"/>
                <texcoord u="0.014200" v="0.340300"/>
            </vertex>
            <vertex>
                <position y="143.966202" x="29.316099" z="-9.448800"/>
                <normal y="-0.423383" x="-0.594012" z="-0.684011"/>
                <texcoord u="0.000500" v="0.010700"/>
            </vertex>
            <vertex>
                <position y="142.971207" x="30.530800" z="-2.980800"/>
                <normal y="-0.994293" x="-0.005463" z="-0.106479"/>
                <texcoord u="0.027900" v="0.669900"/>
            </vertex>
            <vertex>
                <position y="143.197296" x="30.414499" z="0.433600"/>
                <normal y="-0.580706" x="-0.404492" z="0.706504"/>
                <texcoord u="0.041600" v="0.999500"/>
            </vertex>
            <vertex>
                <position y="144.070602" x="32.153500" z="0.314100"/>
                <normal y="-0.118412" x="0.127110" z="0.984771"/>
                <texcoord u="0.367800" v="0.998400"/>
            </vertex>
            <vertex>
                <position y="144.215302" x="32.008701" z="0.350200"/>
                <normal y="-0.118381" x="0.127018" z="0.984802"/>
                <texcoord u="0.367800" v="0.998400"/>
            </vertex>
            <vertex>
                <position y="143.953796" x="31.747801" z="0.352400"/>
                <normal y="-0.118320" x="0.127079" z="0.984802"/>
                <texcoord u="0.302500" v="0.998600"/>
            </vertex>
            <vertex>
                <position y="143.809097" x="31.892500" z="0.316400"/>
                <normal y="-0.118351" x="0.127110" z="0.984771"/>
                <texcoord u="0.302500" v="0.998600"/>
            </vertex>
            <vertex>
                <position y="144.360107" x="31.864000" z="0.386300"/>
                <normal y="-0.118412" x="0.127110" z="0.984771"/>
                <texcoord u="0.367800" v="0.998400"/>
            </vertex>
            <vertex>
                <position y="144.098602" x="31.603001" z="0.388500"/>
                <normal y="-0.118412" x="0.127171" z="0.984771"/>
                <texcoord u="0.302500" v="0.998600"/>
            </vertex>
            <vertex>
                <position y="144.504807" x="31.719299" z="0.422400"/>
                <normal y="-0.118442" x="0.127171" z="0.984771"/>
                <texcoord u="0.367800" v="0.998400"/>
            </vertex>
            <vertex>
                <position y="144.243301" x="31.458300" z="0.424600"/>
                <normal y="-0.118442" x="0.127201" z="0.984771"/>
                <texcoord u="0.302500" v="0.998600"/>
            </vertex>
            <vertex>
                <position y="144.649506" x="31.574499" z="0.458500"/>
                <normal y="-0.118442" x="0.127171" z="0.984771"/>
                <texcoord u="0.367800" v="0.998400"/>
            </vertex>
            <vertex>
                <position y="144.388000" x="31.313601" z="0.460700"/>
                <normal y="-0.118442" x="0.127171" z="0.984771"/>
                <texcoord u="0.302500" v="0.998600"/>
            </vertex>
            <vertex>
                <position y="143.692307" x="31.486799" z="0.354700"/>
                <normal y="-0.118351" x="0.127079" z="0.984802"/>
                <texcoord u="0.237300" v="0.998800"/>
            </vertex>
            <vertex>
                <position y="143.547607" x="31.631599" z="0.318600"/>
                <normal y="-0.118351" x="0.127110" z="0.984771"/>
                <texcoord u="0.237300" v="0.998800"/>
            </vertex>
            <vertex>
                <position y="143.837097" x="31.342100" z="0.390800"/>
                <normal y="-0.118412" x="0.127171" z="0.984771"/>
                <texcoord u="0.237300" v="0.998800"/>
            </vertex>
            <vertex>
                <position y="143.981796" x="31.197399" z="0.426900"/>
                <normal y="-0.118442" x="0.127171" z="0.984771"/>
                <texcoord u="0.237300" v="0.998800"/>
            </vertex>
            <vertex>
                <position y="144.126495" x="31.052601" z="0.463000"/>
                <normal y="-0.118442" x="0.127201" z="0.984771"/>
                <texcoord u="0.237300" v="0.998800"/>
            </vertex>
            <vertex>
                <position y="143.430801" x="31.225901" z="0.356900"/>
                <normal y="-0.118351" x="0.127110" z="0.984771"/>
                <texcoord u="0.172100" v="0.999000"/>
            </vertex>
            <vertex>
                <position y="143.286102" x="31.370600" z="0.320900"/>
                <normal y="-0.118351" x="0.127110" z="0.984771"/>
                <texcoord u="0.172100" v="0.999000"/>
            </vertex>
            <vertex>
                <position y="143.575500" x="31.081200" z="0.393000"/>
                <normal y="-0.118412" x="0.127171" z="0.984771"/>
                <texcoord u="0.172100" v="0.999000"/>
            </vertex>
            <vertex>
                <position y="143.720306" x="30.936399" z="0.429100"/>
                <normal y="-0.118412" x="0.127171" z="0.984771"/>
                <texcoord u="0.172100" v="0.999000"/>
            </vertex>
            <vertex>
                <position y="143.865005" x="30.791700" z="0.465200"/>
                <normal y="-0.118442" x="0.127201" z="0.984771"/>
                <texcoord u="0.172100" v="0.999000"/>
            </vertex>
            <vertex>
                <position y="143.169296" x="30.964899" z="0.359200"/>
                <normal y="-0.118351" x="0.127110" z="0.984771"/>
                <texcoord u="0.106900" v="0.999300"/>
            </vertex>
            <vertex>
                <position y="143.024597" x="31.109699" z="0.323100"/>
                <normal y="-0.118351" x="0.127110" z="0.984771"/>
                <texcoord u="0.106900" v="0.999300"/>
            </vertex>
            <vertex>
                <position y="143.313995" x="30.820200" z="0.395300"/>
                <normal y="-0.118412" x="0.127171" z="0.984771"/>
                <texcoord u="0.106900" v="0.999300"/>
            </vertex>
            <vertex>
                <position y="143.458801" x="30.675501" z="0.431400"/>
                <normal y="-0.118412" x="0.127171" z="0.984771"/>
                <texcoord u="0.106900" v="0.999300"/>
            </vertex>
            <vertex>
                <position y="143.603500" x="30.530800" z="0.467500"/>
                <normal y="-0.118442" x="0.127201" z="0.984771"/>
                <texcoord u="0.106900" v="0.999300"/>
            </vertex>
            <vertex>
                <position y="144.187393" x="32.559101" z="0.275800"/>
                <normal y="-0.163976" x="0.827265" z="0.537309"/>
                <texcoord u="0.433000" v="0.998100"/>
            </vertex>
            <vertex>
                <position y="144.332108" x="32.414398" z="0.311900"/>
                <normal y="0.313761" x="0.513016" z="0.798944"/>
                <texcoord u="0.433000" v="0.998100"/>
            </vertex>
            <vertex>
                <position y="143.925903" x="32.298199" z="0.278000"/>
                <normal y="-0.576159" x="0.582324" z="0.573473"/>
                <texcoord u="0.367800" v="0.998400"/>
            </vertex>
            <vertex>
                <position y="144.794296" x="31.429800" z="0.494600"/>
                <normal y="0.408643" x="-0.402539" z="0.819086"/>
                <texcoord u="0.367800" v="0.998400"/>
            </vertex>
            <vertex>
                <position y="144.910995" x="31.835501" z="0.456200"/>
                <normal y="0.313822" x="0.513047" z="0.798914"/>
                <texcoord u="0.433000" v="0.998100"/>
            </vertex>
            <vertex>
                <position y="145.055801" x="31.690800" z="0.492300"/>
                <normal y="0.667562" x="-0.004059" z="0.744499"/>
                <texcoord u="0.433000" v="0.998100"/>
            </vertex>
            <vertex>
                <position y="143.748199" x="30.386000" z="0.503600"/>
                <normal y="0.408643" x="-0.402448" z="0.819147"/>
                <texcoord u="0.106900" v="0.999300"/>
            </vertex>
            <vertex>
                <position y="142.879898" x="31.254400" z="0.287000"/>
                <normal y="-0.576037" x="0.582415" z="0.573534"/>
                <texcoord u="0.106900" v="0.999300"/>
            </vertex>
            <vertex>
                <position y="144.476807" x="32.269699" z="0.348000"/>
                <normal y="0.313791" x="0.512925" z="0.798975"/>
                <texcoord u="0.433000" v="0.998100"/>
            </vertex>
            <vertex>
                <position y="144.532700" x="31.168900" z="0.496800"/>
                <normal y="0.408643" x="-0.402448" z="0.819147"/>
                <texcoord u="0.302500" v="0.998600"/>
            </vertex>
            <vertex>
                <position y="143.141403" x="31.515301" z="0.284800"/>
                <normal y="-0.576098" x="0.582324" z="0.573565"/>
                <texcoord u="0.172100" v="0.999000"/>
            </vertex>
            <vertex>
                <position y="144.621597" x="32.124901" z="0.384000"/>
                <normal y="0.313883" x="0.513047" z="0.798883"/>
                <texcoord u="0.433000" v="0.998100"/>
            </vertex>
            <vertex>
                <position y="144.271194" x="30.907900" z="0.499100"/>
                <normal y="0.408612" x="-0.402417" z="0.819178"/>
                <texcoord u="0.237300" v="0.998800"/>
            </vertex>
            <vertex>
                <position y="143.402893" x="31.776300" z="0.282500"/>
                <normal y="-0.576159" x="0.582324" z="0.573473"/>
                <texcoord u="0.237300" v="0.998800"/>
            </vertex>
            <vertex>
                <position y="144.766296" x="31.980200" z="0.420100"/>
                <normal y="0.313822" x="0.513047" z="0.798883"/>
                <texcoord u="0.433000" v="0.998100"/>
            </vertex>
            <vertex>
                <position y="144.009705" x="30.646999" z="0.501300"/>
                <normal y="0.408673" x="-0.402417" z="0.819147"/>
                <texcoord u="0.172100" v="0.999000"/>
            </vertex>
            <vertex>
                <position y="143.664398" x="32.037201" z="0.280300"/>
                <normal y="-0.576128" x="0.582232" z="0.573595"/>
                <texcoord u="0.302500" v="0.998600"/>
            </vertex>
            <vertex>
                <position y="145.061096" x="29.539900" z="-9.351300"/>
                <normal y="0.104404" x="-0.141118" z="-0.984466"/>
                <texcoord u="0.165100" v="0.009600"/>
            </vertex>
            <vertex>
                <position y="145.777405" x="30.246300" z="-9.391100"/>
                <normal y="0.094272" x="-0.151067" z="-0.984008"/>
                <texcoord u="0.342800" v="0.005600"/>
            </vertex>
            <vertex>
                <position y="145.632706" x="30.391001" z="-9.427200"/>
                <normal y="0.094272" x="-0.151067" z="-0.984008"/>
                <texcoord u="0.342800" v="0.005600"/>
            </vertex>
            <vertex>
                <position y="144.916306" x="29.684601" z="-9.387400"/>
                <normal y="0.104404" x="-0.141118" z="-0.984466"/>
                <texcoord u="0.165100" v="0.009600"/>
            </vertex>
            <vertex>
                <position y="146.493805" x="30.952801" z="-9.431000"/>
                <normal y="0.104282" x="-0.141026" z="-0.984497"/>
                <texcoord u="0.520400" v="0.001600"/>
            </vertex>
            <vertex>
                <position y="146.349106" x="31.097500" z="-9.467000"/>
                <normal y="0.104282" x="-0.140996" z="-0.984466"/>
                <texcoord u="0.520400" v="0.001600"/>
            </vertex>
            <vertex>
                <position y="147.154404" x="31.610701" z="-9.441800"/>
                <normal y="0.140080" x="-0.105228" z="-0.984527"/>
                <texcoord u="0.685000" v="0.000500"/>
            </vertex>
            <vertex>
                <position y="147.009705" x="31.755400" z="-9.477800"/>
                <normal y="0.140049" x="-0.105258" z="-0.984527"/>
                <texcoord u="0.685000" v="0.000500"/>
            </vertex>
            <vertex>
                <position y="147.703598" x="32.171600" z="-9.394500"/>
                <normal y="0.226569" x="-0.016236" z="-0.973846"/>
                <texcoord u="0.823600" v="0.005300"/>
            </vertex>
            <vertex>
                <position y="147.558899" x="32.316399" z="-9.430600"/>
                <normal y="0.226569" x="-0.016266" z="-0.973846"/>
                <texcoord u="0.823600" v="0.005300"/>
            </vertex>
            <vertex>
                <position y="145.488007" x="30.535801" z="-9.463300"/>
                <normal y="0.094333" x="-0.151097" z="-0.983978"/>
                <texcoord u="0.342800" v="0.005600"/>
            </vertex>
            <vertex>
                <position y="144.771606" x="29.829300" z="-9.423500"/>
                <normal y="0.104404" x="-0.141118" z="-0.984466"/>
                <texcoord u="0.165100" v="0.009600"/>
            </vertex>
            <vertex>
                <position y="146.204407" x="31.242201" z="-9.503100"/>
                <normal y="0.104404" x="-0.141118" z="-0.984466"/>
                <texcoord u="0.520400" v="0.001600"/>
            </vertex>
            <vertex>
                <position y="146.865005" x="31.900200" z="-9.513900"/>
                <normal y="0.140141" x="-0.105319" z="-0.984497"/>
                <texcoord u="0.685000" v="0.000500"/>
            </vertex>
            <vertex>
                <position y="147.414200" x="32.461102" z="-9.466700"/>
                <normal y="0.226478" x="-0.016205" z="-0.973846"/>
                <texcoord u="0.823600" v="0.005300"/>
            </vertex>
            <vertex>
                <position y="145.343201" x="30.680500" z="-9.499400"/>
                <normal y="0.094333" x="-0.151067" z="-0.983978"/>
                <texcoord u="0.342800" v="0.005600"/>
            </vertex>
            <vertex>
                <position y="144.626907" x="29.974001" z="-9.459600"/>
                <normal y="0.104404" x="-0.141118" z="-0.984466"/>
                <texcoord u="0.165100" v="0.009600"/>
            </vertex>
            <vertex>
                <position y="146.059601" x="31.386900" z="-9.539200"/>
                <normal y="0.104404" x="-0.141118" z="-0.984466"/>
                <texcoord u="0.520400" v="0.001600"/>
            </vertex>
            <vertex>
                <position y="146.720306" x="32.044899" z="-9.550000"/>
                <normal y="0.140141" x="-0.105289" z="-0.984497"/>
                <texcoord u="0.685000" v="0.000500"/>
            </vertex>
            <vertex>
                <position y="147.269394" x="32.605801" z="-9.502700"/>
                <normal y="0.226447" x="-0.016175" z="-0.973876"/>
                <texcoord u="0.823600" v="0.005300"/>
            </vertex>
            <vertex>
                <position y="145.198502" x="30.825199" z="-9.535500"/>
                <normal y="0.094272" x="-0.151036" z="-0.984008"/>
                <texcoord u="0.342800" v="0.005600"/>
            </vertex>
            <vertex>
                <position y="144.482101" x="30.118799" z="-9.495700"/>
                <normal y="0.104282" x="-0.140996" z="-0.984497"/>
                <texcoord u="0.165100" v="0.009600"/>
            </vertex>
            <vertex>
                <position y="145.914902" x="31.531700" z="-9.575300"/>
                <normal y="0.104404" x="-0.141118" z="-0.984466"/>
                <texcoord u="0.520400" v="0.001600"/>
            </vertex>
            <vertex>
                <position y="146.575500" x="32.189602" z="-9.586100"/>
                <normal y="0.140202" x="-0.105319" z="-0.984497"/>
                <texcoord u="0.685000" v="0.000500"/>
            </vertex>
            <vertex>
                <position y="147.124695" x="32.750599" z="-9.538800"/>
                <normal y="0.226569" x="-0.016236" z="-0.973846"/>
                <texcoord u="0.823600" v="0.005300"/>
            </vertex>
            <vertex>
                <position y="145.205795" x="29.395100" z="-9.315200"/>
                <normal y="0.564318" x="-0.590411" z="-0.576952"/>
                <texcoord u="0.165100" v="0.009600"/>
            </vertex>
            <vertex>
                <position y="148.085495" x="32.587101" z="-9.260100"/>
                <normal y="0.423688" x="0.203589" z="-0.882626"/>
                <texcoord u="0.923100" v="0.018800"/>
            </vertex>
            <vertex>
                <position y="147.848297" x="32.026901" z="-9.358400"/>
                <normal y="0.643452" x="-0.490768" z="-0.587451"/>
                <texcoord u="0.823600" v="0.005300"/>
            </vertex>
            <vertex>
                <position y="148.230301" x="32.442402" z="-9.224000"/>
                <normal y="0.778130" x="-0.307199" z="-0.547838"/>
                <texcoord u="0.923100" v="0.018800"/>
            </vertex>
            <vertex>
                <position y="147.361893" x="33.310699" z="-9.440500"/>
                <normal y="-0.142094" x="0.612873" z="-0.777276"/>
                <texcoord u="0.923100" v="0.018800"/>
            </vertex>
            <vertex>
                <position y="146.979996" x="32.895302" z="-9.574900"/>
                <normal y="-0.314402" x="0.467147" z="-0.826350"/>
                <texcoord u="0.823600" v="0.005300"/>
            </vertex>
            <vertex>
                <position y="147.506607" x="33.166000" z="-9.404400"/>
                <normal y="0.423597" x="0.203589" z="-0.882656"/>
                <texcoord u="0.923100" v="0.018800"/>
            </vertex>
            <vertex>
                <position y="144.337402" x="30.263500" z="-9.531700"/>
                <normal y="-0.421247" x="0.395398" z="-0.816187"/>
                <texcoord u="0.165100" v="0.009600"/>
            </vertex>
            <vertex>
                <position y="145.922195" x="30.101601" z="-9.355000"/>
                <normal y="0.559069" x="-0.599261" z="-0.572985"/>
                <texcoord u="0.342800" v="0.005600"/>
            </vertex>
            <vertex>
                <position y="147.940796" x="32.731800" z="-9.296200"/>
                <normal y="0.423719" x="0.203589" z="-0.882595"/>
                <texcoord u="0.923100" v="0.018800"/>
            </vertex>
            <vertex>
                <position y="146.430801" x="32.334400" z="-9.622200"/>
                <normal y="-0.386486" x="0.411451" z="-0.825404"/>
                <texcoord u="0.685000" v="0.000500"/>
            </vertex>
            <vertex>
                <position y="146.638504" x="30.808001" z="-9.394900"/>
                <normal y="0.564257" x="-0.590350" z="-0.577105"/>
                <texcoord u="0.520400" v="0.001600"/>
            </vertex>
            <vertex>
                <position y="147.796097" x="32.876499" z="-9.332300"/>
                <normal y="0.423658" x="0.203619" z="-0.882595"/>
                <texcoord u="0.923100" v="0.018800"/>
            </vertex>
            <vertex>
                <position y="145.770203" x="31.676399" z="-9.611400"/>
                <normal y="-0.415662" x="0.389569" z="-0.821833"/>
                <texcoord u="0.520400" v="0.001600"/>
            </vertex>
            <vertex>
                <position y="147.299194" x="31.466000" z="-9.405700"/>
                <normal y="0.586963" x="-0.561998" z="-0.582751"/>
                <texcoord u="0.685000" v="0.000500"/>
            </vertex>
            <vertex>
                <position y="147.651306" x="33.021301" z="-9.368400"/>
                <normal y="0.423566" x="0.203619" z="-0.882656"/>
                <texcoord u="0.923100" v="0.018800"/>
            </vertex>
            <vertex>
                <position y="145.053802" x="30.969999" z="-9.571600"/>
                <normal y="-0.425367" x="0.385205" z="-0.818934"/>
                <texcoord u="0.342800" v="0.005600"/>
            </vertex>
            <vertex>
                <position y="148.276505" x="32.840698" z="-9.008900"/>
                <normal y="0.651509" x="0.511917" z="-0.559862"/>
                <texcoord u="0.978600" v="0.044100"/>
            </vertex>
            <vertex>
                <position y="148.316299" x="32.967899" z="-8.658300"/>
                <normal y="0.716910" x="0.686239" z="-0.122654"/>
                <texcoord u="0.999500" v="0.079500"/>
            </vertex>
            <vertex>
                <position y="148.171600" x="33.112598" z="-8.694400"/>
                <normal y="0.716880" x="0.686270" z="-0.122745"/>
                <texcoord u="0.999500" v="0.079500"/>
            </vertex>
            <vertex>
                <position y="148.131699" x="32.985401" z="-9.045000"/>
                <normal y="0.651448" x="0.511887" z="-0.559923"/>
                <texcoord u="0.978600" v="0.044100"/>
            </vertex>
            <vertex>
                <position y="148.244598" x="32.998100" z="-8.249600"/>
                <normal y="0.673910" x="0.717612" z="0.175573"/>
                <texcoord u="0.994300" v="0.120700"/>
            </vertex>
            <vertex>
                <position y="148.099899" x="33.142899" z="-8.285700"/>
                <normal y="0.673940" x="0.717612" z="0.175573"/>
                <texcoord u="0.994300" v="0.120700"/>
            </vertex>
            <vertex>
                <position y="148.101105" x="32.960701" z="-7.824200"/>
                <normal y="0.622089" x="0.706320" z="0.337718"/>
                <texcoord u="0.971700" v="0.163500"/>
            </vertex>
            <vertex>
                <position y="147.956406" x="33.105400" z="-7.860300"/>
                <normal y="0.622120" x="0.706290" z="0.337748"/>
                <texcoord u="0.971700" v="0.163500"/>
            </vertex>
            <vertex>
                <position y="147.925400" x="32.884899" z="-7.423600"/>
                <normal y="0.583880" x="0.690390" z="0.427045"/>
                <texcoord u="0.940300" v="0.203900"/>
            </vertex>
            <vertex>
                <position y="147.780594" x="33.029598" z="-7.459600"/>
                <normal y="0.583941" x="0.690359" z="0.427045"/>
                <texcoord u="0.940300" v="0.203900"/>
            </vertex>
            <vertex>
                <position y="148.026794" x="33.257401" z="-8.730500"/>
                <normal y="0.716849" x="0.686300" z="-0.122745"/>
                <texcoord u="0.999500" v="0.079500"/>
            </vertex>
            <vertex>
                <position y="147.987000" x="33.130100" z="-9.081100"/>
                <normal y="0.651509" x="0.511856" z="-0.559893"/>
                <texcoord u="0.978600" v="0.044100"/>
            </vertex>
            <vertex>
                <position y="147.955200" x="33.287601" z="-8.321800"/>
                <normal y="0.673818" x="0.717734" z="0.175542"/>
                <texcoord u="0.994300" v="0.120700"/>
            </vertex>
            <vertex>
                <position y="147.811600" x="33.250198" z="-7.896400"/>
                <normal y="0.622089" x="0.706320" z="0.337718"/>
                <texcoord u="0.971700" v="0.163500"/>
            </vertex>
            <vertex>
                <position y="147.635895" x="33.174400" z="-7.495700"/>
                <normal y="0.583941" x="0.690359" z="0.427045"/>
                <texcoord u="0.940300" v="0.203900"/>
            </vertex>
            <vertex>
                <position y="147.882095" x="33.402100" z="-8.766600"/>
                <normal y="0.716910" x="0.686239" z="-0.122715"/>
                <texcoord u="0.999500" v="0.079500"/>
            </vertex>
            <vertex>
                <position y="147.842300" x="33.274799" z="-9.117200"/>
                <normal y="0.651509" x="0.511826" z="-0.559923"/>
                <texcoord u="0.978600" v="0.044100"/>
            </vertex>
            <vertex>
                <position y="147.810394" x="33.432301" z="-8.357900"/>
                <normal y="0.673849" x="0.717673" z="0.175542"/>
                <texcoord u="0.994300" v="0.120700"/>
            </vertex>
            <vertex>
                <position y="147.666901" x="33.394901" z="-7.932500"/>
                <normal y="0.622089" x="0.706351" z="0.337687"/>
                <texcoord u="0.971700" v="0.163500"/>
            </vertex>
            <vertex>
                <position y="147.491196" x="33.319099" z="-7.531800"/>
                <normal y="0.583941" x="0.690359" z="0.427015"/>
                <texcoord u="0.940300" v="0.203900"/>
            </vertex>
            <vertex>
                <position y="147.737396" x="33.546799" z="-8.802700"/>
                <normal y="0.716910" x="0.686239" z="-0.122715"/>
                <texcoord u="0.999500" v="0.079500"/>
            </vertex>
            <vertex>
                <position y="147.697601" x="33.419601" z="-9.153300"/>
                <normal y="0.651479" x="0.511887" z="-0.559923"/>
                <texcoord u="0.978600" v="0.044100"/>
            </vertex>
            <vertex>
                <position y="147.665695" x="33.577099" z="-8.394000"/>
                <normal y="0.673940" x="0.717612" z="0.175573"/>
                <texcoord u="0.994300" v="0.120700"/>
            </vertex>
            <vertex>
                <position y="147.522202" x="33.539600" z="-7.968600"/>
                <normal y="0.622089" x="0.706320" z="0.337718"/>
                <texcoord u="0.971700" v="0.163500"/>
            </vertex>
            <vertex>
                <position y="147.346497" x="33.463799" z="-7.567900"/>
                <normal y="0.583880" x="0.690481" z="0.426954"/>
                <texcoord u="0.940300" v="0.203900"/>
            </vertex>
            <vertex>
                <position y="148.421204" x="32.695900" z="-8.972800"/>
                <normal y="0.947600" x="-0.062685" z="-0.313150"/>
                <texcoord u="0.978600" v="0.044100"/>
            </vertex>
            <vertex>
                <position y="147.757095" x="32.799999" z="-7.089000"/>
                <normal y="0.508316" x="0.649342" z="0.565600"/>
                <texcoord u="0.908700" v="0.237600"/>
            </vertex>
            <vertex>
                <position y="148.070099" x="32.740200" z="-7.387500"/>
                <normal y="0.904294" x="0.007050" z="0.426801"/>
                <texcoord u="0.940300" v="0.203900"/>
            </vertex>
            <vertex>
                <position y="147.901794" x="32.655300" z="-7.052900"/>
                <normal y="0.846156" x="0.003052" z="0.532884"/>
                <texcoord u="0.908700" v="0.237600"/>
            </vertex>
            <vertex>
                <position y="147.033401" x="33.523701" z="-7.269400"/>
                <normal y="-0.100589" x="0.949614" z="0.296731"/>
                <texcoord u="0.908700" v="0.237600"/>
            </vertex>
            <vertex>
                <position y="147.201706" x="33.608501" z="-7.604000"/>
                <normal y="-0.069277" x="0.980499" z="0.183813"/>
                <texcoord u="0.940300" v="0.203900"/>
            </vertex>
            <vertex>
                <position y="147.178207" x="33.379002" z="-7.233300"/>
                <normal y="0.508286" x="0.649373" z="0.565600"/>
                <texcoord u="0.908700" v="0.237600"/>
            </vertex>
            <vertex>
                <position y="147.552795" x="33.564301" z="-9.189400"/>
                <normal y="0.043214" x="0.841426" z="-0.538591"/>
                <texcoord u="0.978600" v="0.044100"/>
            </vertex>
            <vertex>
                <position y="148.460999" x="32.823200" z="-8.622200"/>
                <normal y="0.998535" x="0.048280" z="0.024140"/>
                <texcoord u="0.999500" v="0.079500"/>
            </vertex>
            <vertex>
                <position y="147.612396" x="32.944801" z="-7.125100"/>
                <normal y="0.508316" x="0.649342" z="0.565600"/>
                <texcoord u="0.908700" v="0.237600"/>
            </vertex>
            <vertex>
                <position y="147.377502" x="33.684299" z="-8.004700"/>
                <normal y="-0.034516" x="0.991791" z="0.122959"/>
                <texcoord u="0.971700" v="0.163500"/>
            </vertex>
            <vertex>
                <position y="148.389297" x="32.853401" z="-8.213500"/>
                <normal y="0.967864" x="0.047884" z="0.246834"/>
                <texcoord u="0.994300" v="0.120700"/>
            </vertex>
            <vertex>
                <position y="147.467606" x="33.089500" z="-7.161200"/>
                <normal y="0.508286" x="0.649312" z="0.565661"/>
                <texcoord u="0.908700" v="0.237600"/>
            </vertex>
            <vertex>
                <position y="147.520996" x="33.721802" z="-8.430100"/>
                <normal y="0.015992" x="0.999817" z="0.009461"/>
                <texcoord u="0.994300" v="0.120700"/>
            </vertex>
            <vertex>
                <position y="148.245804" x="32.816002" z="-7.788100"/>
                <normal y="0.931120" x="0.026154" z="0.363750"/>
                <texcoord u="0.971700" v="0.163500"/>
            </vertex>
            <vertex>
                <position y="147.322906" x="33.234200" z="-7.197200"/>
                <normal y="0.508377" x="0.649220" z="0.565722"/>
                <texcoord u="0.908700" v="0.237600"/>
            </vertex>
            <vertex>
                <position y="147.592697" x="33.691502" z="-8.838800"/>
                <normal y="0.071108" x="0.975707" z="-0.207190"/>
                <texcoord u="0.999500" v="0.079500"/>
            </vertex>
            <vertex>
                <position y="147.557205" x="32.664200" z="-6.832300"/>
                <normal y="0.356334" x="0.545518" z="0.758538"/>
                <texcoord u="0.866800" v="0.263500"/>
            </vertex>
            <vertex>
                <position y="147.286301" x="32.445499" z="-6.622800"/>
                <normal y="0.229072" x="0.444868" z="0.865780"/>
                <texcoord u="0.805700" v="0.284600"/>
            </vertex>
            <vertex>
                <position y="147.141495" x="32.590199" z="-6.658800"/>
                <normal y="0.229011" x="0.444899" z="0.865780"/>
                <texcoord u="0.805700" v="0.284600"/>
            </vertex>
            <vertex>
                <position y="147.412506" x="32.808899" z="-6.868400"/>
                <normal y="0.356365" x="0.545518" z="0.758538"/>
                <texcoord u="0.866800" v="0.263500"/>
            </vertex>
            <vertex>
                <position y="146.983093" x="32.188400" z="-6.437900"/>
                <normal y="0.193304" x="0.414869" z="0.889065"/>
                <texcoord u="0.735700" v="0.303300"/>
            </vertex>
            <vertex>
                <position y="146.838303" x="32.333099" z="-6.474000"/>
                <normal y="0.193213" x="0.414960" z="0.889065"/>
                <texcoord u="0.735700" v="0.303300"/>
            </vertex>
            <vertex>
                <position y="146.686600" x="31.937401" z="-6.255300"/>
                <normal y="0.237983" x="0.452162" z="0.859584"/>
                <texcoord u="0.667400" v="0.321700"/>
            </vertex>
            <vertex>
                <position y="146.541901" x="32.082199" z="-6.291400"/>
                <normal y="0.237861" x="0.452254" z="0.859554"/>
                <texcoord u="0.667400" v="0.321700"/>
            </vertex>
            <vertex>
                <position y="146.435699" x="31.737101" z="-6.052600"/>
                <normal y="0.388287" x="0.569048" z="0.724845"/>
                <texcoord u="0.611100" v="0.342100"/>
            </vertex>
            <vertex>
                <position y="146.291000" x="31.881800" z="-6.088700"/>
                <normal y="0.388287" x="0.568987" z="0.724876"/>
                <texcoord u="0.611100" v="0.342100"/>
            </vertex>
            <vertex>
                <position y="146.996796" x="32.734901" z="-6.694900"/>
                <normal y="0.228980" x="0.444929" z="0.865780"/>
                <texcoord u="0.805700" v="0.284600"/>
            </vertex>
            <vertex>
                <position y="147.267807" x="32.953602" z="-6.904500"/>
                <normal y="0.356334" x="0.545549" z="0.758538"/>
                <texcoord u="0.866800" v="0.263500"/>
            </vertex>
            <vertex>
                <position y="146.693604" x="32.477798" z="-6.510100"/>
                <normal y="0.193213" x="0.414960" z="0.889065"/>
                <texcoord u="0.735700" v="0.303300"/>
            </vertex>
            <vertex>
                <position y="146.397095" x="32.226898" z="-6.327500"/>
                <normal y="0.237861" x="0.452315" z="0.859523"/>
                <texcoord u="0.667400" v="0.321700"/>
            </vertex>
            <vertex>
                <position y="146.146301" x="32.026600" z="-6.124800"/>
                <normal y="0.388195" x="0.569048" z="0.724876"/>
                <texcoord u="0.611100" v="0.342100"/>
            </vertex>
            <vertex>
                <position y="146.852097" x="32.879601" z="-6.731000"/>
                <normal y="0.229041" x="0.444868" z="0.865780"/>
                <texcoord u="0.805700" v="0.284600"/>
            </vertex>
            <vertex>
                <position y="147.123001" x="33.098400" z="-6.940600"/>
                <normal y="0.356426" x="0.545396" z="0.758568"/>
                <texcoord u="0.866800" v="0.263500"/>
            </vertex>
            <vertex>
                <position y="146.548904" x="32.622601" z="-6.546200"/>
                <normal y="0.193213" x="0.414930" z="0.889065"/>
                <texcoord u="0.735700" v="0.303300"/>
            </vertex>
            <vertex>
                <position y="146.252396" x="32.371601" z="-6.363600"/>
                <normal y="0.237861" x="0.452284" z="0.859554"/>
                <texcoord u="0.667400" v="0.321700"/>
            </vertex>
            <vertex>
                <position y="146.001495" x="32.171299" z="-6.160900"/>
                <normal y="0.388195" x="0.569140" z="0.724815"/>
                <texcoord u="0.611100" v="0.342100"/>
            </vertex>
            <vertex>
                <position y="146.707306" x="33.024399" z="-6.767100"/>
                <normal y="0.228980" x="0.444868" z="0.865810"/>
                <texcoord u="0.805700" v="0.284600"/>
            </vertex>
            <vertex>
                <position y="146.978302" x="33.243099" z="-6.976600"/>
                <normal y="0.356334" x="0.545427" z="0.758599"/>
                <texcoord u="0.866800" v="0.263500"/>
            </vertex>
            <vertex>
                <position y="146.404205" x="32.767300" z="-6.582300"/>
                <normal y="0.193182" x="0.414960" z="0.889065"/>
                <texcoord u="0.735700" v="0.303300"/>
            </vertex>
            <vertex>
                <position y="146.107697" x="32.516300" z="-6.399700"/>
                <normal y="0.237922" x="0.452223" z="0.859554"/>
                <texcoord u="0.667400" v="0.321700"/>
            </vertex>
            <vertex>
                <position y="145.856796" x="32.316002" z="-6.197000"/>
                <normal y="0.388318" x="0.568957" z="0.724876"/>
                <texcoord u="0.611100" v="0.342100"/>
            </vertex>
            <vertex>
                <position y="147.701996" x="32.519501" z="-6.796200"/>
                <normal y="0.733665" x="-0.069735" z="0.675893"/>
                <texcoord u="0.866800" v="0.263500"/>
            </vertex>
            <vertex>
                <position y="146.269302" x="31.631901" z="-5.807200"/>
                <normal y="0.613941" x="0.703421" z="0.358074"/>
                <texcoord u="0.577200" v="0.366800"/>
            </vertex>
            <vertex>
                <position y="146.580399" x="31.592400" z="-6.016500"/>
                <normal y="0.772118" x="-0.111942" z="0.625538"/>
                <texcoord u="0.611100" v="0.342100"/>
            </vertex>
            <vertex>
                <position y="146.414093" x="31.487200" z="-5.771100"/>
                <normal y="0.927671" x="-0.096683" z="0.360637"/>
                <texcoord u="0.577200" v="0.366800"/>
            </vertex>
            <vertex>
                <position y="145.545700" x="32.355598" z="-5.987700"/>
                <normal y="-0.133427" x="0.986053" z="0.099399"/>
                <texcoord u="0.577200" v="0.366800"/>
            </vertex>
            <vertex>
                <position y="145.712097" x="32.460701" z="-6.233000"/>
                <normal y="-0.262337" x="0.898495" z="0.351909"/>
                <texcoord u="0.611100" v="0.342100"/>
            </vertex>
            <vertex>
                <position y="145.690399" x="32.210800" z="-5.951600"/>
                <normal y="0.614124" x="0.703238" z="0.358135"/>
                <texcoord u="0.577200" v="0.366800"/>
            </vertex>
            <vertex>
                <position y="146.833603" x="33.387798" z="-7.012700"/>
                <normal y="-0.208869" x="0.872829" z="0.441054"/>
                <texcoord u="0.866800" v="0.263500"/>
            </vertex>
            <vertex>
                <position y="147.431000" x="32.300701" z="-6.586700"/>
                <normal y="0.649098" x="-0.165136" z="0.742515"/>
                <texcoord u="0.805700" v="0.284600"/>
            </vertex>
            <vertex>
                <position y="146.124603" x="31.776600" z="-5.843300"/>
                <normal y="0.614124" x="0.703238" z="0.358135"/>
                <texcoord u="0.577200" v="0.366800"/>
            </vertex>
            <vertex>
                <position y="145.962997" x="32.661098" z="-6.435800"/>
                <normal y="-0.311197" x="0.808618" z="0.499222"/>
                <texcoord u="0.667400" v="0.321700"/>
            </vertex>
            <vertex>
                <position y="147.127808" x="32.043598" z="-6.401800"/>
                <normal y="0.629231" x="-0.199530" z="0.751122"/>
                <texcoord u="0.735700" v="0.303300"/>
            </vertex>
            <vertex>
                <position y="145.979904" x="31.921400" z="-5.879400"/>
                <normal y="0.614002" x="0.703330" z="0.358135"/>
                <texcoord u="0.577200" v="0.366800"/>
            </vertex>
            <vertex>
                <position y="146.259399" x="32.911999" z="-6.618400"/>
                <normal y="-0.356243" x="0.785943" z="0.505325"/>
                <texcoord u="0.735700" v="0.303300"/>
            </vertex>
            <vertex>
                <position y="146.831299" x="31.792700" z="-6.219300"/>
                <normal y="0.657674" x="-0.165319" z="0.734916"/>
                <texcoord u="0.667400" v="0.321700"/>
            </vertex>
            <vertex>
                <position y="145.835098" x="32.066101" z="-5.915500"/>
                <normal y="0.613910" x="0.703452" z="0.358074"/>
                <texcoord u="0.577200" v="0.366800"/>
            </vertex>
            <vertex>
                <position y="146.562607" x="33.169102" z="-6.803200"/>
                <normal y="-0.319224" x="0.803827" z="0.501907"/>
                <texcoord u="0.805700" v="0.284600"/>
            </vertex>
            <vertex>
                <position y="146.219193" x="31.648300" z="-5.540500"/>
                <normal y="0.717307" x="0.682546" z="-0.139836"/>
                <texcoord u="0.572900" v="0.393700"/>
            </vertex>
            <vertex>
                <position y="146.260696" x="31.756001" z="-5.274800"/>
                <normal y="0.689047" x="0.580859" z="-0.433302"/>
                <texcoord u="0.591600" v="0.420500"/>
            </vertex>
            <vertex>
                <position y="146.115997" x="31.900801" z="-5.310900"/>
                <normal y="0.688986" x="0.580889" z="-0.433363"/>
                <texcoord u="0.591600" v="0.420500"/>
            </vertex>
            <vertex>
                <position y="146.074493" x="31.792999" z="-5.576600"/>
                <normal y="0.717429" x="0.682394" z="-0.139805"/>
                <texcoord u="0.572900" v="0.393700"/>
            </vertex>
            <vertex>
                <position y="146.347702" x="31.914400" z="-4.988800"/>
                <normal y="0.675253" x="0.553484" z="-0.487472"/>
                <texcoord u="0.622200" v="0.449300"/>
            </vertex>
            <vertex>
                <position y="146.203003" x="32.059101" z="-5.024900"/>
                <normal y="0.675161" x="0.553575" z="-0.487503"/>
                <texcoord u="0.622200" v="0.449300"/>
            </vertex>
            <vertex>
                <position y="146.434402" x="32.082699" z="-4.661600"/>
                <normal y="0.698691" x="0.602405" z="-0.385876"/>
                <texcoord u="0.654000" v="0.482300"/>
            </vertex>
            <vertex>
                <position y="146.289703" x="32.227402" z="-4.697700"/>
                <normal y="0.698660" x="0.602466" z="-0.385846"/>
                <texcoord u="0.654000" v="0.482300"/>
            </vertex>
            <vertex>
                <position y="146.474899" x="32.220299" z="-4.271900"/>
                <normal y="0.717643" x="0.677419" z="-0.161382"/>
                <texcoord u="0.676300" v="0.521600"/>
            </vertex>
            <vertex>
                <position y="146.330093" x="32.365002" z="-4.308000"/>
                <normal y="0.717582" x="0.677480" z="-0.161382"/>
                <texcoord u="0.676300" v="0.521600"/>
            </vertex>
            <vertex>
                <position y="145.971207" x="32.045502" z="-5.346900"/>
                <normal y="0.688925" x="0.580981" z="-0.433363"/>
                <texcoord u="0.591600" v="0.420500"/>
            </vertex>
            <vertex>
                <position y="145.929794" x="31.937799" z="-5.612700"/>
                <normal y="0.717338" x="0.682546" z="-0.139775"/>
                <texcoord u="0.572900" v="0.393700"/>
            </vertex>
            <vertex>
                <position y="146.058304" x="32.203800" z="-5.061000"/>
                <normal y="0.675100" x="0.553606" z="-0.487564"/>
                <texcoord u="0.622200" v="0.449300"/>
            </vertex>
            <vertex>
                <position y="146.145004" x="32.372101" z="-4.733800"/>
                <normal y="0.698691" x="0.602405" z="-0.385846"/>
                <texcoord u="0.654000" v="0.482300"/>
            </vertex>
            <vertex>
                <position y="146.185394" x="32.509701" z="-4.344100"/>
                <normal y="0.717704" x="0.677358" z="-0.161351"/>
                <texcoord u="0.676300" v="0.521600"/>
            </vertex>
            <vertex>
                <position y="145.826508" x="32.190201" z="-5.383000"/>
                <normal y="0.688955" x="0.580920" z="-0.433363"/>
                <texcoord u="0.591600" v="0.420500"/>
            </vertex>
            <vertex>
                <position y="145.785004" x="32.082500" z="-5.648800"/>
                <normal y="0.717277" x="0.682577" z="-0.139775"/>
                <texcoord u="0.572900" v="0.393700"/>
            </vertex>
            <vertex>
                <position y="145.913498" x="32.348598" z="-5.097100"/>
                <normal y="0.675130" x="0.553575" z="-0.487564"/>
                <texcoord u="0.622200" v="0.449300"/>
            </vertex>
            <vertex>
                <position y="146.000198" x="32.516899" z="-4.769900"/>
                <normal y="0.698630" x="0.602466" z="-0.385876"/>
                <texcoord u="0.654000" v="0.482300"/>
            </vertex>
            <vertex>
                <position y="146.040695" x="32.654499" z="-4.380200"/>
                <normal y="0.717673" x="0.677389" z="-0.161382"/>
                <texcoord u="0.676300" v="0.521600"/>
            </vertex>
            <vertex>
                <position y="145.681793" x="32.334900" z="-5.419100"/>
                <normal y="0.689016" x="0.580889" z="-0.433332"/>
                <texcoord u="0.591600" v="0.420500"/>
            </vertex>
            <vertex>
                <position y="145.640305" x="32.227200" z="-5.684900"/>
                <normal y="0.717460" x="0.682424" z="-0.139714"/>
                <texcoord u="0.572900" v="0.393700"/>
            </vertex>
            <vertex>
                <position y="145.768799" x="32.493301" z="-5.133200"/>
                <normal y="0.675161" x="0.553545" z="-0.487533"/>
                <texcoord u="0.622200" v="0.449300"/>
            </vertex>
            <vertex>
                <position y="145.855499" x="32.661598" z="-4.805900"/>
                <normal y="0.698630" x="0.602496" z="-0.385846"/>
                <texcoord u="0.654000" v="0.482300"/>
            </vertex>
            <vertex>
                <position y="145.895905" x="32.799198" z="-4.416300"/>
                <normal y="0.717582" x="0.677480" z="-0.161443"/>
                <texcoord u="0.676300" v="0.521600"/>
            </vertex>
            <vertex>
                <position y="146.363998" x="31.503599" z="-5.504400"/>
                <normal y="0.998474" x="0.054323" z="0.009339"/>
                <texcoord u="0.572900" v="0.393700"/>
            </vertex>
            <vertex>
                <position y="146.423096" x="32.286499" z="-3.798800"/>
                <normal y="0.693472" x="0.715201" z="0.086856"/>
                <texcoord u="0.678100" v="0.569300"/>
            </vertex>
            <vertex>
                <position y="146.619598" x="32.075500" z="-4.235900"/>
                <normal y="0.999603" x="0.027253" z="-0.001343"/>
                <texcoord u="0.676300" v="0.521600"/>
            </vertex>
            <vertex>
                <position y="146.567795" x="32.141800" z="-3.762700"/>
                <normal y="0.982177" x="0.046327" z="0.182043"/>
                <texcoord u="0.678100" v="0.569300"/>
            </vertex>
            <vertex>
                <position y="145.699402" x="33.010101" z="-3.979200"/>
                <normal y="0.030427" x="0.997986" z="-0.055208"/>
                <texcoord u="0.678100" v="0.569300"/>
            </vertex>
            <vertex>
                <position y="145.751205" x="32.943901" z="-4.452400"/>
                <normal y="0.057527" x="0.969939" z="-0.236366"/>
                <texcoord u="0.676300" v="0.521600"/>
            </vertex>
            <vertex>
                <position y="145.844193" x="32.865398" z="-3.943200"/>
                <normal y="0.693381" x="0.715293" z="0.086825"/>
                <texcoord u="0.678100" v="0.569300"/>
            </vertex>
            <vertex>
                <position y="145.495605" x="32.372002" z="-5.721000"/>
                <normal y="-0.066256" x="0.972594" z="-0.222816"/>
                <texcoord u="0.572900" v="0.393700"/>
            </vertex>
            <vertex>
                <position y="146.405396" x="31.611300" z="-5.238700"/>
                <normal y="0.979369" x="-0.106326" z="-0.171728"/>
                <texcoord u="0.591600" v="0.420500"/>
            </vertex>
            <vertex>
                <position y="146.278397" x="32.431198" z="-3.834900"/>
                <normal y="0.693411" x="0.715262" z="0.086856"/>
                <texcoord u="0.678100" v="0.569300"/>
            </vertex>
            <vertex>
                <position y="145.710800" x="32.806301" z="-4.842000"/>
                <normal y="0.030244" x="0.916105" z="-0.399762"/>
                <texcoord u="0.654000" v="0.482300"/>
            </vertex>
            <vertex>
                <position y="146.492401" x="31.769600" z="-4.952700"/>
                <normal y="0.969756" x="-0.097934" z="-0.223487"/>
                <texcoord u="0.622200" v="0.449300"/>
            </vertex>
            <vertex>
                <position y="146.133606" x="32.575901" z="-3.871000"/>
                <normal y="0.693564" x="0.715110" z="0.086886"/>
                <texcoord u="0.678100" v="0.569300"/>
            </vertex>
            <vertex>
                <position y="145.624100" x="32.638000" z="-5.169300"/>
                <normal y="-0.008332" x="0.883145" z="-0.468978"/>
                <texcoord u="0.622200" v="0.449300"/>
            </vertex>
            <vertex>
                <position y="146.579102" x="31.938000" z="-4.625500"/>
                <normal y="0.986053" x="-0.039979" z="-0.161443"/>
                <texcoord u="0.654000" v="0.482300"/>
            </vertex>
            <vertex>
                <position y="145.988907" x="32.720699" z="-3.907100"/>
                <normal y="0.693564" x="0.715110" z="0.086856"/>
                <texcoord u="0.678100" v="0.569300"/>
            </vertex>
            <vertex>
                <position y="145.537003" x="32.479698" z="-5.455200"/>
                <normal y="-0.032105" x="0.905087" z="-0.423963"/>
                <texcoord u="0.591600" v="0.420500"/>
            </vertex>
            <vertex>
                <position y="146.267502" x="32.275299" z="-3.219600"/>
                <normal y="0.657247" x="0.716025" z="0.235145"/>
                <texcoord u="0.657200" v="0.627600"/>
            </vertex>
            <vertex>
                <position y="146.042404" x="32.217999" z="-2.546900"/>
                <normal y="0.637165" x="0.711264" z="0.296762"/>
                <texcoord u="0.622000" v="0.695500"/>
            </vertex>
            <vertex>
                <position y="145.897705" x="32.362801" z="-2.583000"/>
                <normal y="0.637257" x="0.711173" z="0.296793"/>
                <texcoord u="0.622000" v="0.695500"/>
            </vertex>
            <vertex>
                <position y="146.122696" x="32.419998" z="-3.255700"/>
                <normal y="0.657338" x="0.715964" z="0.235145"/>
                <texcoord u="0.657200" v="0.627600"/>
            </vertex>
            <vertex>
                <position y="145.771194" x="32.130100" z="-1.811700"/>
                <normal y="0.626545" x="0.707938" z="0.325938"/>
                <texcoord u="0.577200" v="0.769600"/>
            </vertex>
            <vertex>
                <position y="145.626404" x="32.274799" z="-1.847800"/>
                <normal y="0.626545" x="0.707907" z="0.325968"/>
                <texcoord u="0.577200" v="0.769600"/>
            </vertex>
            <vertex>
                <position y="145.476700" x="32.026798" z="-1.045300"/>
                <normal y="0.623249" x="0.706717" z="0.334727"/>
                <texcoord u="0.527500" v="0.846800"/>
            </vertex>
            <vertex>
                <position y="145.332001" x="32.171501" z="-1.081400"/>
                <normal y="0.623249" x="0.706748" z="0.334697"/>
                <texcoord u="0.527500" v="0.846800"/>
            </vertex>
            <vertex>
                <position y="145.182297" x="31.923401" z="-0.278900"/>
                <normal y="0.626606" x="0.707816" z="0.325999"/>
                <texcoord u="0.477800" v="0.924000"/>
            </vertex>
            <vertex>
                <position y="145.037598" x="32.068199" z="-0.315000"/>
                <normal y="0.626606" x="0.707816" z="0.325999"/>
                <texcoord u="0.477800" v="0.924000"/>
            </vertex>
            <vertex>
                <position y="145.753006" x="32.507500" z="-2.619000"/>
                <normal y="0.637287" x="0.711142" z="0.296823"/>
                <texcoord u="0.622000" v="0.695500"/>
            </vertex>
            <vertex>
                <position y="145.977997" x="32.564800" z="-3.291800"/>
                <normal y="0.657399" x="0.715903" z="0.235115"/>
                <texcoord u="0.657200" v="0.627600"/>
            </vertex>
            <vertex>
                <position y="145.481705" x="32.419498" z="-1.883900"/>
                <normal y="0.626637" x="0.707816" z="0.325999"/>
                <texcoord u="0.577200" v="0.769600"/>
            </vertex>
            <vertex>
                <position y="145.187302" x="32.316200" z="-1.117500"/>
                <normal y="0.623249" x="0.706748" z="0.334697"/>
                <texcoord u="0.527500" v="0.846800"/>
            </vertex>
            <vertex>
                <position y="144.892899" x="32.212898" z="-0.351100"/>
                <normal y="0.626514" x="0.707938" z="0.325968"/>
                <texcoord u="0.477800" v="0.924000"/>
            </vertex>
            <vertex>
                <position y="145.608307" x="32.652199" z="-2.655100"/>
                <normal y="0.637196" x="0.711234" z="0.296793"/>
                <texcoord u="0.622000" v="0.695500"/>
            </vertex>
            <vertex>
                <position y="145.833298" x="32.709499" z="-3.327900"/>
                <normal y="0.657338" x="0.715934" z="0.235115"/>
                <texcoord u="0.657200" v="0.627600"/>
            </vertex>
            <vertex>
                <position y="145.337006" x="32.564301" z="-1.920000"/>
                <normal y="0.626576" x="0.707877" z="0.325999"/>
                <texcoord u="0.577200" v="0.769600"/>
            </vertex>
            <vertex>
                <position y="145.042603" x="32.460899" z="-1.153600"/>
                <normal y="0.623249" x="0.706748" z="0.334697"/>
                <texcoord u="0.527500" v="0.846800"/>
            </vertex>
            <vertex>
                <position y="144.748093" x="32.357601" z="-0.387200"/>
                <normal y="0.626576" x="0.707877" z="0.325999"/>
                <texcoord u="0.477800" v="0.924000"/>
            </vertex>
            <vertex>
                <position y="145.463501" x="32.797001" z="-2.691200"/>
                <normal y="0.637165" x="0.711264" z="0.296762"/>
                <texcoord u="0.622000" v="0.695500"/>
            </vertex>
            <vertex>
                <position y="145.688599" x="32.854198" z="-3.364000"/>
                <normal y="0.657247" x="0.716056" z="0.235084"/>
                <texcoord u="0.657200" v="0.627600"/>
            </vertex>
            <vertex>
                <position y="145.192200" x="32.709000" z="-1.956100"/>
                <normal y="0.626545" x="0.707907" z="0.325999"/>
                <texcoord u="0.577200" v="0.769600"/>
            </vertex>
            <vertex>
                <position y="144.897797" x="32.605701" z="-1.189700"/>
                <normal y="0.623280" x="0.706717" z="0.334697"/>
                <texcoord u="0.527500" v="0.846800"/>
            </vertex>
            <vertex>
                <position y="144.603394" x="32.502399" z="-0.423300"/>
                <normal y="0.626606" x="0.707846" z="0.325999"/>
                <texcoord u="0.477800" v="0.924000"/>
            </vertex>
            <vertex>
                <position y="146.412201" x="32.130600" z="-3.183500"/>
                <normal y="0.956725" x="0.027345" z="0.289590"/>
                <texcoord u="0.657200" v="0.627600"/>
            </vertex>
            <vertex>
                <position y="145.326996" x="31.778700" z="-0.242900"/>
                <normal y="0.935606" x="0.005127" z="0.352947"/>
                <texcoord u="0.477800" v="0.924000"/>
            </vertex>
            <vertex>
                <position y="144.458694" x="32.647099" z="-0.459400"/>
                <normal y="-0.046541" x="0.992950" z="0.108768"/>
                <texcoord u="0.477800" v="0.924000"/>
            </vertex>
            <vertex>
                <position y="145.543793" x="32.998901" z="-3.400100"/>
                <normal y="-0.014863" x="0.998749" z="0.047273"/>
                <texcoord u="0.657200" v="0.627600"/>
            </vertex>
            <vertex>
                <position y="146.187195" x="32.073299" z="-2.510800"/>
                <normal y="0.942656" x="0.017396" z="0.333232"/>
                <texcoord u="0.622000" v="0.695500"/>
            </vertex>
            <vertex>
                <position y="144.753098" x="32.750401" z="-1.225800"/>
                <normal y="-0.051668" x="0.992126" z="0.113865"/>
                <texcoord u="0.527500" v="0.846800"/>
            </vertex>
            <vertex>
                <position y="145.915894" x="31.985399" z="-1.775600"/>
                <normal y="0.935392" x="0.009949" z="0.353465"/>
                <texcoord u="0.577200" v="0.769600"/>
            </vertex>
            <vertex>
                <position y="145.047501" x="32.853699" z="-1.992100"/>
                <normal y="-0.045442" x="0.992950" z="0.109195"/>
                <texcoord u="0.577200" v="0.769600"/>
            </vertex>
            <vertex>
                <position y="145.621506" x="31.882000" z="-1.009200"/>
                <normal y="0.933164" x="0.006043" z="0.359355"/>
                <texcoord u="0.527500" v="0.846800"/>
            </vertex>
            <vertex>
                <position y="145.318802" x="32.941700" z="-2.727300"/>
                <normal y="-0.035371" x="0.995361" z="0.089328"/>
                <texcoord u="0.622000" v="0.695500"/>
            </vertex>
        </vertexbuffer>
    </sharedgeometry>
    <submeshes>
        <submesh usesharedvertices="true" material="hull_trim_wood" use32bitindexes="False" operationtype="triangle_list">
            <faces count="584">
                <face v1="0" v2="1" v3="2"/>
                <face v1="0" v2="2" v3="3"/>
                <face v1="1" v2="4" v3="5"/>
                <face v1="1" v2="5" v3="2"/>
                <face v1="4" v2="6" v3="7"/>
                <face v1="4" v2="7" v3="5"/>
                <face v1="6" v2="8" v3="9"/>
                <face v1="6" v2="9" v3="7"/>
                <face v1="3" v2="2" v3="10"/>
                <face v1="3" v2="10" v3="11"/>
                <face v1="2" v2="5" v3="12"/>
                <face v1="2" v2="12" v3="10"/>
                <face v1="5" v2="7" v3="13"/>
                <face v1="5" v2="13" v3="12"/>
                <face v1="7" v2="9" v3="14"/>
                <face v1="7" v2="14" v3="13"/>
                <face v1="11" v2="10" v3="15"/>
                <face v1="11" v2="15" v3="16"/>
                <face v1="10" v2="12" v3="17"/>
                <face v1="10" v2="17" v3="15"/>
                <face v1="12" v2="13" v3="18"/>
                <face v1="12" v2="18" v3="17"/>
                <face v1="13" v2="14" v3="19"/>
                <face v1="13" v2="19" v3="18"/>
                <face v1="16" v2="15" v3="20"/>
                <face v1="16" v2="20" v3="21"/>
                <face v1="15" v2="17" v3="22"/>
                <face v1="15" v2="22" v3="20"/>
                <face v1="17" v2="18" v3="23"/>
                <face v1="17" v2="23" v3="22"/>
                <face v1="18" v2="19" v3="24"/>
                <face v1="18" v2="24" v3="23"/>
                <face v1="0" v2="25" v3="26"/>
                <face v1="0" v2="26" v3="27"/>
                <face v1="28" v2="8" v3="29"/>
                <face v1="28" v2="29" v3="30"/>
                <face v1="31" v2="32" v3="24"/>
                <face v1="31" v2="24" v3="33"/>
                <face v1="34" v2="21" v3="35"/>
                <face v1="34" v2="35" v3="36"/>
                <face v1="1" v2="0" v3="27"/>
                <face v1="1" v2="27" v3="37"/>
                <face v1="38" v2="9" v3="8"/>
                <face v1="38" v2="8" v3="28"/>
                <face v1="32" v2="39" v3="23"/>
                <face v1="32" v2="23" v3="24"/>
                <face v1="40" v2="16" v3="21"/>
                <face v1="40" v2="21" v3="34"/>
                <face v1="37" v2="41" v3="4"/>
                <face v1="37" v2="4" v3="1"/>
                <face v1="42" v2="14" v3="9"/>
                <face v1="42" v2="9" v3="38"/>
                <face v1="39" v2="43" v3="22"/>
                <face v1="39" v2="22" v3="23"/>
                <face v1="44" v2="11" v3="16"/>
                <face v1="44" v2="16" v3="40"/>
                <face v1="41" v2="45" v3="6"/>
                <face v1="41" v2="6" v3="4"/>
                <face v1="46" v2="19" v3="14"/>
                <face v1="46" v2="14" v3="42"/>
                <face v1="43" v2="47" v3="20"/>
                <face v1="43" v2="20" v3="22"/>
                <face v1="48" v2="3" v3="11"/>
                <face v1="48" v2="11" v3="44"/>
                <face v1="45" v2="29" v3="8"/>
                <face v1="45" v2="8" v3="6"/>
                <face v1="33" v2="24" v3="19"/>
                <face v1="33" v2="19" v3="46"/>
                <face v1="47" v2="35" v3="21"/>
                <face v1="47" v2="21" v3="20"/>
                <face v1="25" v2="0" v3="3"/>
                <face v1="25" v2="3" v3="48"/>
                <face v1="49" v2="50" v3="51"/>
                <face v1="49" v2="51" v3="52"/>
                <face v1="50" v2="53" v3="54"/>
                <face v1="50" v2="54" v3="51"/>
                <face v1="53" v2="55" v3="56"/>
                <face v1="53" v2="56" v3="54"/>
                <face v1="55" v2="57" v3="58"/>
                <face v1="55" v2="58" v3="56"/>
                <face v1="52" v2="51" v3="59"/>
                <face v1="52" v2="59" v3="60"/>
                <face v1="51" v2="54" v3="61"/>
                <face v1="51" v2="61" v3="59"/>
                <face v1="54" v2="56" v3="62"/>
                <face v1="54" v2="62" v3="61"/>
                <face v1="56" v2="58" v3="63"/>
                <face v1="56" v2="63" v3="62"/>
                <face v1="60" v2="59" v3="64"/>
                <face v1="60" v2="64" v3="65"/>
                <face v1="59" v2="61" v3="66"/>
                <face v1="59" v2="66" v3="64"/>
                <face v1="61" v2="62" v3="67"/>
                <face v1="61" v2="67" v3="66"/>
                <face v1="62" v2="63" v3="68"/>
                <face v1="62" v2="68" v3="67"/>
                <face v1="65" v2="64" v3="69"/>
                <face v1="65" v2="69" v3="70"/>
                <face v1="64" v2="66" v3="71"/>
                <face v1="64" v2="71" v3="69"/>
                <face v1="66" v2="67" v3="72"/>
                <face v1="66" v2="72" v3="71"/>
                <face v1="67" v2="68" v3="73"/>
                <face v1="67" v2="73" v3="72"/>
                <face v1="74" v2="75" v3="49"/>
                <face v1="74" v2="49" v3="76"/>
                <face v1="77" v2="57" v3="78"/>
                <face v1="77" v2="78" v3="79"/>
                <face v1="26" v2="25" v3="73"/>
                <face v1="26" v2="73" v3="80"/>
                <face v1="81" v2="70" v3="34"/>
                <face v1="81" v2="34" v3="36"/>
                <face v1="75" v2="82" v3="50"/>
                <face v1="75" v2="50" v3="49"/>
                <face v1="83" v2="58" v3="57"/>
                <face v1="83" v2="57" v3="77"/>
                <face v1="25" v2="48" v3="72"/>
                <face v1="25" v2="72" v3="73"/>
                <face v1="84" v2="65" v3="70"/>
                <face v1="84" v2="70" v3="81"/>
                <face v1="82" v2="85" v3="53"/>
                <face v1="82" v2="53" v3="50"/>
                <face v1="86" v2="63" v3="58"/>
                <face v1="86" v2="58" v3="83"/>
                <face v1="48" v2="44" v3="71"/>
                <face v1="48" v2="71" v3="72"/>
                <face v1="87" v2="60" v3="65"/>
                <face v1="87" v2="65" v3="84"/>
                <face v1="85" v2="88" v3="55"/>
                <face v1="85" v2="55" v3="53"/>
                <face v1="89" v2="68" v3="63"/>
                <face v1="89" v2="63" v3="86"/>
                <face v1="44" v2="40" v3="69"/>
                <face v1="44" v2="69" v3="71"/>
                <face v1="90" v2="52" v3="60"/>
                <face v1="90" v2="60" v3="87"/>
                <face v1="88" v2="78" v3="57"/>
                <face v1="88" v2="57" v3="55"/>
                <face v1="80" v2="73" v3="68"/>
                <face v1="80" v2="68" v3="89"/>
                <face v1="40" v2="34" v3="70"/>
                <face v1="40" v2="70" v3="69"/>
                <face v1="76" v2="49" v3="52"/>
                <face v1="76" v2="52" v3="90"/>
                <face v1="91" v2="92" v3="93"/>
                <face v1="91" v2="93" v3="94"/>
                <face v1="92" v2="95" v3="96"/>
                <face v1="92" v2="96" v3="93"/>
                <face v1="95" v2="97" v3="98"/>
                <face v1="95" v2="98" v3="96"/>
                <face v1="97" v2="99" v3="100"/>
                <face v1="97" v2="100" v3="98"/>
                <face v1="94" v2="93" v3="101"/>
                <face v1="94" v2="101" v3="102"/>
                <face v1="93" v2="96" v3="103"/>
                <face v1="93" v2="103" v3="101"/>
                <face v1="96" v2="98" v3="104"/>
                <face v1="96" v2="104" v3="103"/>
                <face v1="98" v2="100" v3="105"/>
                <face v1="98" v2="105" v3="104"/>
                <face v1="102" v2="101" v3="106"/>
                <face v1="102" v2="106" v3="107"/>
                <face v1="101" v2="103" v3="108"/>
                <face v1="101" v2="108" v3="106"/>
                <face v1="103" v2="104" v3="109"/>
                <face v1="103" v2="109" v3="108"/>
                <face v1="104" v2="105" v3="110"/>
                <face v1="104" v2="110" v3="109"/>
                <face v1="107" v2="106" v3="111"/>
                <face v1="107" v2="111" v3="112"/>
                <face v1="106" v2="108" v3="113"/>
                <face v1="106" v2="113" v3="111"/>
                <face v1="108" v2="109" v3="114"/>
                <face v1="108" v2="114" v3="113"/>
                <face v1="109" v2="110" v3="115"/>
                <face v1="109" v2="115" v3="114"/>
                <face v1="30" v2="116" v3="91"/>
                <face v1="30" v2="91" v3="28"/>
                <face v1="117" v2="99" v3="118"/>
                <face v1="117" v2="118" v3="119"/>
                <face v1="120" v2="121" v3="115"/>
                <face v1="120" v2="115" v3="122"/>
                <face v1="33" v2="112" v3="123"/>
                <face v1="33" v2="123" v3="31"/>
                <face v1="116" v2="124" v3="92"/>
                <face v1="116" v2="92" v3="91"/>
                <face v1="125" v2="100" v3="99"/>
                <face v1="125" v2="99" v3="117"/>
                <face v1="121" v2="126" v3="114"/>
                <face v1="121" v2="114" v3="115"/>
                <face v1="46" v2="107" v3="112"/>
                <face v1="46" v2="112" v3="33"/>
                <face v1="124" v2="127" v3="95"/>
                <face v1="124" v2="95" v3="92"/>
                <face v1="128" v2="105" v3="100"/>
                <face v1="128" v2="100" v3="125"/>
                <face v1="126" v2="129" v3="113"/>
                <face v1="126" v2="113" v3="114"/>
                <face v1="42" v2="102" v3="107"/>
                <face v1="42" v2="107" v3="46"/>
                <face v1="127" v2="130" v3="97"/>
                <face v1="127" v2="97" v3="95"/>
                <face v1="131" v2="110" v3="105"/>
                <face v1="131" v2="105" v3="128"/>
                <face v1="129" v2="132" v3="111"/>
                <face v1="129" v2="111" v3="113"/>
                <face v1="38" v2="94" v3="102"/>
                <face v1="38" v2="102" v3="42"/>
                <face v1="130" v2="118" v3="99"/>
                <face v1="130" v2="99" v3="97"/>
                <face v1="122" v2="115" v3="110"/>
                <face v1="122" v2="110" v3="131"/>
                <face v1="132" v2="123" v3="112"/>
                <face v1="132" v2="112" v3="111"/>
                <face v1="28" v2="91" v3="94"/>
                <face v1="28" v2="94" v3="38"/>
                <face v1="133" v2="134" v3="135"/>
                <face v1="133" v2="135" v3="136"/>
                <face v1="134" v2="137" v3="138"/>
                <face v1="134" v2="138" v3="135"/>
                <face v1="137" v2="139" v3="140"/>
                <face v1="137" v2="140" v3="138"/>
                <face v1="139" v2="141" v3="142"/>
                <face v1="139" v2="142" v3="140"/>
                <face v1="136" v2="135" v3="143"/>
                <face v1="136" v2="143" v3="144"/>
                <face v1="135" v2="138" v3="145"/>
                <face v1="135" v2="145" v3="143"/>
                <face v1="138" v2="140" v3="146"/>
                <face v1="138" v2="146" v3="145"/>
                <face v1="140" v2="142" v3="147"/>
                <face v1="140" v2="147" v3="146"/>
                <face v1="144" v2="143" v3="148"/>
                <face v1="144" v2="148" v3="149"/>
                <face v1="143" v2="145" v3="150"/>
                <face v1="143" v2="150" v3="148"/>
                <face v1="145" v2="146" v3="151"/>
                <face v1="145" v2="151" v3="150"/>
                <face v1="146" v2="147" v3="152"/>
                <face v1="146" v2="152" v3="151"/>
                <face v1="149" v2="148" v3="153"/>
                <face v1="149" v2="153" v3="154"/>
                <face v1="148" v2="150" v3="155"/>
                <face v1="148" v2="155" v3="153"/>
                <face v1="150" v2="151" v3="156"/>
                <face v1="150" v2="156" v3="155"/>
                <face v1="151" v2="152" v3="157"/>
                <face v1="151" v2="157" v3="156"/>
                <face v1="119" v2="158" v3="133"/>
                <face v1="119" v2="133" v3="117"/>
                <face v1="159" v2="141" v3="160"/>
                <face v1="159" v2="160" v3="161"/>
                <face v1="162" v2="163" v3="157"/>
                <face v1="162" v2="157" v3="164"/>
                <face v1="122" v2="154" v3="165"/>
                <face v1="122" v2="165" v3="120"/>
                <face v1="158" v2="166" v3="134"/>
                <face v1="158" v2="134" v3="133"/>
                <face v1="167" v2="142" v3="141"/>
                <face v1="167" v2="141" v3="159"/>
                <face v1="163" v2="168" v3="156"/>
                <face v1="163" v2="156" v3="157"/>
                <face v1="131" v2="149" v3="154"/>
                <face v1="131" v2="154" v3="122"/>
                <face v1="166" v2="169" v3="137"/>
                <face v1="166" v2="137" v3="134"/>
                <face v1="170" v2="147" v3="142"/>
                <face v1="170" v2="142" v3="167"/>
                <face v1="168" v2="171" v3="155"/>
                <face v1="168" v2="155" v3="156"/>
                <face v1="128" v2="144" v3="149"/>
                <face v1="128" v2="149" v3="131"/>
                <face v1="169" v2="172" v3="139"/>
                <face v1="169" v2="139" v3="137"/>
                <face v1="173" v2="152" v3="147"/>
                <face v1="173" v2="147" v3="170"/>
                <face v1="171" v2="174" v3="153"/>
                <face v1="171" v2="153" v3="155"/>
                <face v1="125" v2="136" v3="144"/>
                <face v1="125" v2="144" v3="128"/>
                <face v1="172" v2="160" v3="141"/>
                <face v1="172" v2="141" v3="139"/>
                <face v1="164" v2="157" v3="152"/>
                <face v1="164" v2="152" v3="173"/>
                <face v1="174" v2="165" v3="154"/>
                <face v1="174" v2="154" v3="153"/>
                <face v1="117" v2="133" v3="136"/>
                <face v1="117" v2="136" v3="125"/>
                <face v1="175" v2="176" v3="177"/>
                <face v1="175" v2="177" v3="178"/>
                <face v1="176" v2="179" v3="180"/>
                <face v1="176" v2="180" v3="177"/>
                <face v1="179" v2="181" v3="182"/>
                <face v1="179" v2="182" v3="180"/>
                <face v1="181" v2="183" v3="184"/>
                <face v1="181" v2="184" v3="182"/>
                <face v1="178" v2="177" v3="185"/>
                <face v1="178" v2="185" v3="186"/>
                <face v1="177" v2="180" v3="187"/>
                <face v1="177" v2="187" v3="185"/>
                <face v1="180" v2="182" v3="188"/>
                <face v1="180" v2="188" v3="187"/>
                <face v1="182" v2="184" v3="189"/>
                <face v1="182" v2="189" v3="188"/>
                <face v1="186" v2="185" v3="190"/>
                <face v1="186" v2="190" v3="191"/>
                <face v1="185" v2="187" v3="192"/>
                <face v1="185" v2="192" v3="190"/>
                <face v1="187" v2="188" v3="193"/>
                <face v1="187" v2="193" v3="192"/>
                <face v1="188" v2="189" v3="194"/>
                <face v1="188" v2="194" v3="193"/>
                <face v1="191" v2="190" v3="195"/>
                <face v1="191" v2="195" v3="196"/>
                <face v1="190" v2="192" v3="197"/>
                <face v1="190" v2="197" v3="195"/>
                <face v1="192" v2="193" v3="198"/>
                <face v1="192" v2="198" v3="197"/>
                <face v1="193" v2="194" v3="199"/>
                <face v1="193" v2="199" v3="198"/>
                <face v1="161" v2="200" v3="175"/>
                <face v1="161" v2="175" v3="159"/>
                <face v1="201" v2="183" v3="202"/>
                <face v1="201" v2="202" v3="203"/>
                <face v1="204" v2="205" v3="199"/>
                <face v1="204" v2="199" v3="206"/>
                <face v1="164" v2="196" v3="207"/>
                <face v1="164" v2="207" v3="162"/>
                <face v1="200" v2="208" v3="176"/>
                <face v1="200" v2="176" v3="175"/>
                <face v1="209" v2="184" v3="183"/>
                <face v1="209" v2="183" v3="201"/>
                <face v1="205" v2="210" v3="198"/>
                <face v1="205" v2="198" v3="199"/>
                <face v1="173" v2="191" v3="196"/>
                <face v1="173" v2="196" v3="164"/>
                <face v1="208" v2="211" v3="179"/>
                <face v1="208" v2="179" v3="176"/>
                <face v1="212" v2="189" v3="184"/>
                <face v1="212" v2="184" v3="209"/>
                <face v1="210" v2="213" v3="197"/>
                <face v1="210" v2="197" v3="198"/>
                <face v1="170" v2="186" v3="191"/>
                <face v1="170" v2="191" v3="173"/>
                <face v1="211" v2="214" v3="181"/>
                <face v1="211" v2="181" v3="179"/>
                <face v1="215" v2="194" v3="189"/>
                <face v1="215" v2="189" v3="212"/>
                <face v1="213" v2="216" v3="195"/>
                <face v1="213" v2="195" v3="197"/>
                <face v1="167" v2="178" v3="186"/>
                <face v1="167" v2="186" v3="170"/>
                <face v1="214" v2="202" v3="183"/>
                <face v1="214" v2="183" v3="181"/>
                <face v1="206" v2="199" v3="194"/>
                <face v1="206" v2="194" v3="215"/>
                <face v1="216" v2="207" v3="196"/>
                <face v1="216" v2="196" v3="195"/>
                <face v1="159" v2="175" v3="178"/>
                <face v1="159" v2="178" v3="167"/>
                <face v1="217" v2="218" v3="219"/>
                <face v1="217" v2="219" v3="220"/>
                <face v1="218" v2="221" v3="222"/>
                <face v1="218" v2="222" v3="219"/>
                <face v1="221" v2="223" v3="224"/>
                <face v1="221" v2="224" v3="222"/>
                <face v1="223" v2="225" v3="226"/>
                <face v1="223" v2="226" v3="224"/>
                <face v1="220" v2="219" v3="227"/>
                <face v1="220" v2="227" v3="228"/>
                <face v1="219" v2="222" v3="229"/>
                <face v1="219" v2="229" v3="227"/>
                <face v1="222" v2="224" v3="230"/>
                <face v1="222" v2="230" v3="229"/>
                <face v1="224" v2="226" v3="231"/>
                <face v1="224" v2="231" v3="230"/>
                <face v1="228" v2="227" v3="232"/>
                <face v1="228" v2="232" v3="233"/>
                <face v1="227" v2="229" v3="234"/>
                <face v1="227" v2="234" v3="232"/>
                <face v1="229" v2="230" v3="235"/>
                <face v1="229" v2="235" v3="234"/>
                <face v1="230" v2="231" v3="236"/>
                <face v1="230" v2="236" v3="235"/>
                <face v1="233" v2="232" v3="237"/>
                <face v1="233" v2="237" v3="238"/>
                <face v1="232" v2="234" v3="239"/>
                <face v1="232" v2="239" v3="237"/>
                <face v1="234" v2="235" v3="240"/>
                <face v1="234" v2="240" v3="239"/>
                <face v1="235" v2="236" v3="241"/>
                <face v1="235" v2="241" v3="240"/>
                <face v1="203" v2="242" v3="217"/>
                <face v1="203" v2="217" v3="201"/>
                <face v1="243" v2="225" v3="244"/>
                <face v1="243" v2="244" v3="245"/>
                <face v1="246" v2="247" v3="241"/>
                <face v1="246" v2="241" v3="248"/>
                <face v1="206" v2="238" v3="249"/>
                <face v1="206" v2="249" v3="204"/>
                <face v1="242" v2="250" v3="218"/>
                <face v1="242" v2="218" v3="217"/>
                <face v1="251" v2="226" v3="225"/>
                <face v1="251" v2="225" v3="243"/>
                <face v1="247" v2="252" v3="240"/>
                <face v1="247" v2="240" v3="241"/>
                <face v1="215" v2="233" v3="238"/>
                <face v1="215" v2="238" v3="206"/>
                <face v1="250" v2="253" v3="221"/>
                <face v1="250" v2="221" v3="218"/>
                <face v1="254" v2="231" v3="226"/>
                <face v1="254" v2="226" v3="251"/>
                <face v1="252" v2="255" v3="239"/>
                <face v1="252" v2="239" v3="240"/>
                <face v1="212" v2="228" v3="233"/>
                <face v1="212" v2="233" v3="215"/>
                <face v1="253" v2="256" v3="223"/>
                <face v1="253" v2="223" v3="221"/>
                <face v1="257" v2="236" v3="231"/>
                <face v1="257" v2="231" v3="254"/>
                <face v1="255" v2="258" v3="237"/>
                <face v1="255" v2="237" v3="239"/>
                <face v1="209" v2="220" v3="228"/>
                <face v1="209" v2="228" v3="212"/>
                <face v1="256" v2="244" v3="225"/>
                <face v1="256" v2="225" v3="223"/>
                <face v1="248" v2="241" v3="236"/>
                <face v1="248" v2="236" v3="257"/>
                <face v1="258" v2="249" v3="238"/>
                <face v1="258" v2="238" v3="237"/>
                <face v1="201" v2="217" v3="220"/>
                <face v1="201" v2="220" v3="209"/>
                <face v1="259" v2="260" v3="261"/>
                <face v1="259" v2="261" v3="262"/>
                <face v1="260" v2="263" v3="264"/>
                <face v1="260" v2="264" v3="261"/>
                <face v1="263" v2="265" v3="266"/>
                <face v1="263" v2="266" v3="264"/>
                <face v1="265" v2="267" v3="268"/>
                <face v1="265" v2="268" v3="266"/>
                <face v1="262" v2="261" v3="269"/>
                <face v1="262" v2="269" v3="270"/>
                <face v1="261" v2="264" v3="271"/>
                <face v1="261" v2="271" v3="269"/>
                <face v1="264" v2="266" v3="272"/>
                <face v1="264" v2="272" v3="271"/>
                <face v1="266" v2="268" v3="273"/>
                <face v1="266" v2="273" v3="272"/>
                <face v1="270" v2="269" v3="274"/>
                <face v1="270" v2="274" v3="275"/>
                <face v1="269" v2="271" v3="276"/>
                <face v1="269" v2="276" v3="274"/>
                <face v1="271" v2="272" v3="277"/>
                <face v1="271" v2="277" v3="276"/>
                <face v1="272" v2="273" v3="278"/>
                <face v1="272" v2="278" v3="277"/>
                <face v1="275" v2="274" v3="279"/>
                <face v1="275" v2="279" v3="280"/>
                <face v1="274" v2="276" v3="281"/>
                <face v1="274" v2="281" v3="279"/>
                <face v1="276" v2="277" v3="282"/>
                <face v1="276" v2="282" v3="281"/>
                <face v1="277" v2="278" v3="283"/>
                <face v1="277" v2="283" v3="282"/>
                <face v1="245" v2="284" v3="259"/>
                <face v1="245" v2="259" v3="243"/>
                <face v1="78" v2="267" v3="285"/>
                <face v1="78" v2="285" v3="79"/>
                <face v1="74" v2="286" v3="283"/>
                <face v1="74" v2="283" v3="75"/>
                <face v1="248" v2="280" v3="287"/>
                <face v1="248" v2="287" v3="246"/>
                <face v1="284" v2="288" v3="260"/>
                <face v1="284" v2="260" v3="259"/>
                <face v1="88" v2="268" v3="267"/>
                <face v1="88" v2="267" v3="78"/>
                <face v1="286" v2="289" v3="282"/>
                <face v1="286" v2="282" v3="283"/>
                <face v1="257" v2="275" v3="280"/>
                <face v1="257" v2="280" v3="248"/>
                <face v1="288" v2="290" v3="263"/>
                <face v1="288" v2="263" v3="260"/>
                <face v1="85" v2="273" v3="268"/>
                <face v1="85" v2="268" v3="88"/>
                <face v1="289" v2="291" v3="281"/>
                <face v1="289" v2="281" v3="282"/>
                <face v1="254" v2="270" v3="275"/>
                <face v1="254" v2="275" v3="257"/>
                <face v1="290" v2="292" v3="265"/>
                <face v1="290" v2="265" v3="263"/>
                <face v1="82" v2="278" v3="273"/>
                <face v1="82" v2="273" v3="85"/>
                <face v1="291" v2="293" v3="279"/>
                <face v1="291" v2="279" v3="281"/>
                <face v1="251" v2="262" v3="270"/>
                <face v1="251" v2="270" v3="254"/>
                <face v1="292" v2="285" v3="267"/>
                <face v1="292" v2="267" v3="265"/>
                <face v1="75" v2="283" v3="278"/>
                <face v1="75" v2="278" v3="82"/>
                <face v1="293" v2="287" v3="280"/>
                <face v1="293" v2="280" v3="279"/>
                <face v1="243" v2="259" v3="262"/>
                <face v1="243" v2="262" v3="251"/>
                <face v1="77" v2="79" v3="285"/>
                <face v1="77" v2="285" v3="83"/>
                <face v1="86" v2="83" v3="285"/>
                <face v1="86" v2="285" v3="89"/>
                <face v1="292" v2="290" v3="288"/>
                <face v1="292" v2="288" v3="285"/>
                <face v1="288" v2="284" v3="245"/>
                <face v1="288" v2="245" v3="256"/>
                <face v1="245" v2="244" v3="256"/>
                <face v1="285" v2="288" v3="256"/>
                <face v1="285" v2="256" v3="250"/>
                <face v1="256" v2="253" v3="250"/>
                <face v1="89" v2="285" v3="250"/>
                <face v1="89" v2="250" v3="45"/>
                <face v1="211" v2="208" v3="200"/>
                <face v1="211" v2="200" v3="214"/>
                <face v1="200" v2="161" v3="160"/>
                <face v1="200" v2="160" v3="169"/>
                <face v1="160" v2="172" v3="169"/>
                <face v1="214" v2="200" v3="169"/>
                <face v1="214" v2="169" v3="202"/>
                <face v1="169" v2="166" v3="158"/>
                <face v1="169" v2="158" v3="118"/>
                <face v1="158" v2="119" v3="118"/>
                <face v1="118" v2="130" v3="127"/>
                <face v1="118" v2="127" v3="124"/>
                <face v1="169" v2="118" v3="124"/>
                <face v1="169" v2="124" v3="45"/>
                <face v1="116" v2="30" v3="29"/>
                <face v1="116" v2="29" v3="124"/>
                <face v1="124" v2="29" v3="45"/>
                <face v1="202" v2="169" v3="45"/>
                <face v1="202" v2="45" v3="203"/>
                <face v1="242" v2="203" v3="45"/>
                <face v1="242" v2="45" v3="250"/>
                <face v1="80" v2="89" v3="45"/>
                <face v1="80" v2="45" v3="41"/>
                <face v1="80" v2="41" v3="37"/>
                <face v1="80" v2="37" v3="27"/>
                <face v1="26" v2="80" v3="27"/>
                <face v1="132" v2="129" v3="126"/>
                <face v1="132" v2="126" v3="123"/>
                <face v1="126" v2="121" v3="120"/>
                <face v1="126" v2="120" v3="174"/>
                <face v1="120" v2="165" v3="174"/>
                <face v1="123" v2="126" v3="174"/>
                <face v1="123" v2="174" v3="213"/>
                <face v1="174" v2="171" v3="168"/>
                <face v1="174" v2="168" v3="162"/>
                <face v1="168" v2="163" v3="162"/>
                <face v1="162" v2="207" v3="216"/>
                <face v1="162" v2="216" v3="213"/>
                <face v1="174" v2="162" v3="213"/>
                <face v1="123" v2="213" v3="210"/>
                <face v1="123" v2="210" v3="205"/>
                <face v1="123" v2="205" v3="204"/>
                <face v1="123" v2="204" v3="35"/>
                <face v1="258" v2="255" v3="252"/>
                <face v1="258" v2="252" v3="246"/>
                <face v1="252" v2="247" v3="246"/>
                <face v1="249" v2="258" v3="246"/>
                <face v1="249" v2="246" v3="76"/>
                <face v1="246" v2="287" v3="293"/>
                <face v1="246" v2="293" v3="289"/>
                <face v1="293" v2="291" v3="289"/>
                <face v1="286" v2="74" v3="76"/>
                <face v1="286" v2="76" v3="289"/>
                <face v1="246" v2="289" v3="76"/>
                <face v1="204" v2="249" v3="76"/>
                <face v1="204" v2="76" v3="35"/>
                <face v1="81" v2="36" v3="35"/>
                <face v1="81" v2="35" v3="84"/>
                <face v1="87" v2="84" v3="35"/>
                <face v1="87" v2="35" v3="90"/>
                <face v1="76" v2="90" v3="35"/>
                <face v1="123" v2="35" v3="47"/>
                <face v1="123" v2="47" v3="43"/>
                <face v1="123" v2="43" v3="39"/>
                <face v1="123" v2="39" v3="32"/>
                <face v1="31" v2="123" v3="32"/>
            </faces>
        </submesh>
    </submeshes>
    <submeshnames>
        <submesh index="0" name="hull_trim_wood">
        </submesh>
    </submeshnames>
</mesh>